Workbook

Sheet Scraper-Verified
A1: ID | B1: Address | C1: Latitude | D1: Longitude | E1: Phone Number | F1: Name of Service | G1: Restrictions of Service | H1: Days of Service | I1: Cateogry of Help | J1: Description | K1: link to site | L1: Reliability Description | M1: Reliability Score | N1: Confidence | O1: Confidence Details | P1: Date Verified | Q1: Classification
A2: 1 | B2: 1731 E Chase St, Baltimore, MD 21213 | C2: 39.303176 | D2: -76.592979 | E2: (410) 545-0136 | F2: The Community Resource Center | G2: Residents in catchment area | H2: Monday: 8:30 AM to 4:30 PM; Tuesday: 8:30 AM to 4:30 PM; Wednesday: 8:30 AM to 4:30 PM; Thursday: 8:30 AM to 4:30 PM; Friday: 8:30 AM to 4:30 PM; Saturday: Closed; Sunday: Closed | I2: Other / Uncategorized | J2: A physical community resource center located at the supplied Baltimore address. Publicly available sources do not provide clear, attributable details about specific programs, eligibility rules, or services offered at this location. | L2: Public review text is sparse: most Google reviewers left star ratings without comments, so substantive feedback is limited. The few written comments report crowding and at least one complaint about perceived staff impatience; several recent anonymous low-star ratings exist but provide no explanatory detail. Because review content is thin and the organization’s website could not be verified, qualitative impressions are provisional. | M2: 67.472471 | N2: 47.576945 | O2: accepted google identity: 14.2/15; review volume: 22.1/30; review consistency: 2.3/7; review freshness: 7.3/8; verified website: 0.0/15; confirmed irs record: 0.0/20; source corroboration: 1.7/5; Synthesis metadata: insufficient_evidence (not part of numeric confidence) | P2: 8312026 | Q2: =IF(OR(ISBLANK(M2), ISBLANK(N2)), "", IF(N2 < Sheet3!$B$6, "Insufficient Reviews", IF(M2 >= Sheet3!$B$2, "Highly Reliable", IF(M2 >= Sheet3!$B$3, "Reliable", IF(M2 >= Sheet3!$B$4, "Mixed Reviews", "Low Reliability"))))) -> Mixed Reviews
A3: =A2+1 -> 2 | B3: 5225 York Rd #4, Baltimore, MD 21212 | C3: 39.35388 | D3: -76.609677 | E3: (410) 396-6084 | F3: Northern Community Action | G3: Residents in catchment area | H3: Monday: 8:30 AM to 3:30 PM; Tuesday: 8:30 AM to 3:30 PM; Wednesday: 8:30 AM to 3:30 PM; Thursday: 8:30 AM to 3:30 PM; Friday: 8:30 AM to 3:30 PM; Saturday: Closed; Sunday: Closed | I3: Youth, Family, & General Support Services | J3: A neighborhood community center / social services office that provides in-person assistance and referrals to other agencies for residents seeking help with social supports and benefit programs. | L3: Review text shows a mix of experiences: many reviewers describe staff as helpful and able to provide resources or get things done, while a recurring negative theme is long wait times and occasional reports of rude or unprofessional staff. The most recent reviews continue to show this mixed pattern, with some recent 5-star praise alongside isolated low-star reports about service and wait time. Attempts to corroborate program details on an official website were unsuccessful, which limits confirmation of specific services beyond what reviewers report and the Google listing. | M3: 67.055632 | N3: 54.105562 | O3: accepted google identity: 14.2/15; review volume: 30.0/30; review consistency: 1.0/7; review freshness: 7.2/8; verified website: 0.0/15; confirmed irs record: 0.0/20; source corroboration: 1.7/5; Synthesis metadata: medium (not part of numeric confidence) | P3: 8312026 | Q3: =IF(OR(ISBLANK(M3), ISBLANK(N3)), "", IF(N3 < Sheet3!$B$6, "Insufficient Reviews", IF(M3 >= Sheet3!$B$2, "Highly Reliable", IF(M3 >= Sheet3!$B$3, "Reliable", IF(M3 >= Sheet3!$B$4, "Mixed Reviews", "Low Reliability"))))) -> Mixed Reviews
A4: =A3+1 -> 3 | B4: Tower II, 100 S Charles St 8th floor, Baltimore, MD 21201 | C4: 39.286971 | D4: -76.615731 | E4: (410) 637-1900 | F4: Behavioral Health System Baltimore | G4: 988 crisis support is available by call or text and is described as free and confidential for residents in Baltimore City, Baltimore County, Howard County, and Carroll County. Bmore POWER provides citywide harm-reduction outreach and posts an outreach schedule; materials and services referenced include naloxone and drug-testing resources. No additional intake documents, referral-only restrictions, or eligibility requirements were stated in the available sources. | H4: Monday: 8 AM to 5 PM; Tuesday: 8 AM to 5 PM; Wednesday: 8 AM to 5 PM; Thursday: 8 AM to 5 PM; Friday: 8 AM to 5 PM; Saturday: Closed; Sunday: Closed | I4: Behavioral Health, Substance Use, & Crisis | J4: A city-level behavioral health coordinating organization that operates a 988 crisis helpline for the region, runs a harm-reduction outreach team (Bmore POWER) offering on-the-ground outreach and overdose-harm-reduction services, and manages complaints and system navigation for behavioral-health providers in Baltimore City. | K4: http://www.bhsbaltimore.org/ | L4: Public review feedback is very limited; the available recent review expresses that the reviewer felt their concerns were ignored and reports distrust of health-care professionals, and the listing owner did not post a response. The organization’s official website and archival snapshots corroborate described programs (988 helpline, Bmore POWER outreach, complaint management), supporting the identity and stated activities. Because review text is sparse and skewed negative, user-experience claims should be treated cautiously and are not broadly generalizable. | M4: 46.873173 | N4: 71.549732 | O4: accepted google identity: 14.2/15; review volume: 8.9/30; review consistency: 7.0/7; review freshness: 2.2/8; verified website: 14.2/15; confirmed irs record: 20.0/20; source corroboration: 5.0/5; Synthesis metadata: high (not part of numeric confidence) | P4: 8312026 | Q4: =IF(OR(ISBLANK(M4), ISBLANK(N4)), "", IF(N4 < Sheet3!$B$6, "Insufficient Reviews", IF(M4 >= Sheet3!$B$2, "Highly Reliable", IF(M4 >= Sheet3!$B$3, "Reliable", IF(M4 >= Sheet3!$B$4, "Mixed Reviews", "Low Reliability"))))) -> Low Reliability
A5: =A4+1 -> 4 | B5: 4200 Pennington Ave, Baltimore, MD 21226 | C5: 39.227395 | D5: -76.58888 | E5: (443) 300-1177 | F5: Unlimited Bounds Human Services | G5: Contact an admissions coordinator to begin services (phone and contact form available); the website states an admissions coordinator will respond within two business days. Prospective clients are asked to contact admissions to confirm insurance acceptance and intake details; the site describes an intake team that facilitates initiation of services. | H5: Monday: 9 AM to 5 PM; Tuesday: 9 AM to 5 PM; Wednesday: 9 AM to 5 PM; Thursday: 9 AM to 5 PM; Friday: 9 AM to 5 PM; Saturday: 9 AM to 5 PM; Sunday: 9 AM to 5 PM | I5: Behavioral Health, Substance Use, & Crisis | J5: A Baltimore-based behavioral health provider offering multi-level addiction treatment and associated mental health care, including structured day programs, outpatient treatment, individual and group therapy, medication management, residential/housing support, and telehealth options. | K5: https://unlimitedbounds.com/ | L5: Google Maps reviews show a substantial set of first-hand client feedback: many reviewers praise caring, committed staff and describe effective PHP/IOP programming, on-site housing, and meals; recurring criticisms include staff turnover, small food portions, and delays or problems getting psychiatric medications. The organization’s verified website and Google Maps listing consistently describe a multi-level addiction-treatment continuum (PHP, IOP, outpatient), residential/housing services, medication management/psychiatry, and telehealth, which aligns with reviewer accounts. Newer reviews continue to show a mix of strong endorsements and sharp operational complaints, so public feedback is mixed but consistent with the services advertised. | M5: 71.935244 | N5: 69.45683 | O5: accepted google identity: 13.5/15; review volume: 30.0/30; review consistency: 1.4/7; review freshness: 7.7/8; verified website: 13.5/15; confirmed irs record: 0.0/20; source corroboration: 3.3/5; Synthesis metadata: high (not part of numeric confidence) | P5: 8312026 | Q5: =IF(OR(ISBLANK(M5), ISBLANK(N5)), "", IF(N5 < Sheet3!$B$6, "Insufficient Reviews", IF(M5 >= Sheet3!$B$2, "Highly Reliable", IF(M5 >= Sheet3!$B$3, "Reliable", IF(M5 >= Sheet3!$B$4, "Mixed Reviews", "Low Reliability"))))) -> Reliable
A6: =A5+1 -> 5 | B6: 4201 Primrose Ave, Baltimore, MD 21215 | C6: 39.349402 | D6: -76.695859 | E6: (410) 764-8560 | F6: People Encouraging People | G6: Enrollment in PEP services is implied for ongoing support; the website instructs enrolled clients to call their usual PEP office and notes an after-hours on-call number will connect when needed. (Evidence: official website and Google Maps listing.) | H6: Monday: 8:30 AM to 5 PM; Tuesday: 8:30 AM to 5 PM; Wednesday: 8:30 AM to 5 PM; Thursday: 8:30 AM to 5 PM; Friday: 8:30 AM to 5 PM; Saturday: Closed; Sunday: Closed | I6: Behavioral Health, Substance Use, & Crisis | J6: PEP (People Encouraging People) operates a physical recovery/behavioral health program that provides community-based rehabilitation and individualized support services for people with psychiatric or other disabling conditions; the organization’s website also states it is accredited by The Joint Commission. | K6: http://www.peponline.org/ | L6: Recent reviewer comments are mixed: many people report helpful, caring, communicative staff who supported intake, housing assistance, or other services, while other reviewers describe serious safety and housing-related problems at some PEP sites, including allegations of unaddressed violence and pest issues. The most recent reviews include both brief positive reports and one detailed, severe complaint about a past site, so public feedback is currently mixed rather than uniformly positive or uniformly negative. | M6: 69.190493 | N6: 70.645529 | O6: accepted google identity: 14.2/15; review volume: 30.0/30; review consistency: 3.0/7; review freshness: 5.8/8; verified website: 14.2/15; confirmed irs record: 0.0/20; source corroboration: 3.3/5; Synthesis metadata: medium (not part of numeric confidence) | P6: 8312026 | Q6: =IF(OR(ISBLANK(M6), ISBLANK(N6)), "", IF(N6 < Sheet3!$B$6, "Insufficient Reviews", IF(M6 >= Sheet3!$B$2, "Highly Reliable", IF(M6 >= Sheet3!$B$3, "Reliable", IF(M6 >= Sheet3!$B$4, "Mixed Reviews", "Low Reliability"))))) -> Mixed Reviews
A7: =A6+1 -> 6 | B7: 25 S Charles St, Baltimore, MD 21201 | C7: 39.288203 | D7: -76.61451 | E7: (800) 332-6347 | F7: Maryland Department of Human Services | G7: Contact DHS for services and intake by phone (1-800-332-6347) with TTY 1-800-735-2258; report adult or child abuse via the dedicated hotline (1-800-917-7383). SNAP and energy-assistance programs require application/eligibility processes (energy-assistance program year runs 7/1–6/30). Child Protective Services uses investigative or alternative responses depending on assessed risk. (Access details as stated on DHS website and the Google Maps listing.) | H7: Monday: 8:30 AM to 5 PM; Tuesday: 8:30 AM to 5 PM; Wednesday: 8:30 AM to 5 PM; Thursday: 8:30 AM to 5 PM; Friday: 8:30 AM to 5 PM; Saturday: Closed; Sunday: Closed | I7: Food & Essential Needs | J7: Maryland Department of Human Services operates statewide social-service programs including adult services (support for elderly and adults with disabilities), child protective services, administration of food benefits (SNAP), and energy/utility assistance programs. | K7: http://dhs.maryland.gov/ | L7: Google reviewers most frequently report long phone wait times, lost paperwork, communication breakdowns, and negative experiences with staff responsiveness—some reviewers describe serious problems with adult protective services responses. Recurring positive comments note that individual staff or front-desk workers can be helpful and patient when reached. The newest reviews continue to emphasize frustration and perceived systemic inefficiency, while positive experiences remain present but less common. | M7: 46.883036 | N7: 70.64272 | O7: accepted google identity: 14.2/15; review volume: 30.0/30; review consistency: 1.0/7; review freshness: 7.8/8; verified website: 14.2/15; confirmed irs record: 0.0/20; source corroboration: 3.3/5; Synthesis metadata: high (not part of numeric confidence) | P7: 8312026 | Q7: =IF(OR(ISBLANK(M7), ISBLANK(N7)), "", IF(N7 < Sheet3!$B$6, "Insufficient Reviews", IF(M7 >= Sheet3!$B$2, "Highly Reliable", IF(M7 >= Sheet3!$B$3, "Reliable", IF(M7 >= Sheet3!$B$4, "Mixed Reviews", "Low Reliability"))))) -> Low Reliability
A8: =A7+1 -> 7 | B8: 3549 Old Frederick Rd, Baltimore, MD 21229 | C8: 39.28273 | D8: -76.676759 | E8: (410) 837-1400 | F8: Project Plase | G8: Intake requires completing an intake application; SSVF and some veteran programs are for qualified veterans and may prioritize chronically homeless veterans. Some programs require case management intake and referrals. Site accessibility features reported (wheelchair accessible entrance and parking). | H8: Monday: 9 AM to 3 PM; Tuesday: 9 AM to 3 PM; Wednesday: 9 AM to 3 PM; Thursday: 9 AM to 3 PM; Friday: 9 AM to 3 PM; Saturday: Closed; Sunday: Closed | I8: Housing & Shelter | J8: Project PLASE provides temporary emergency housing and longer-term supportive and subsidized housing programs, plus case management and wraparound supportive services (including a veteran-focused SSVF program) to help people move from homelessness into stable housing. | K8: https://projectplase.org/ | L8: Google reviewers commonly report that staff are helpful and that the program has assisted people in obtaining safe, stable housing; several reviews specifically praise staff and the program’s housing outcomes. Recurring negative feedback centers on at least one user being told help was unavailable after arrival, indicating occasional access or capacity problems. The recent reviews in the sample remain largely positive, and organizational identity is corroborated by an IRS registry match and an official website. | M8: 82.134922 | N8: 92.168783 | O8: accepted google identity: 13.5/15; review volume: 30.0/30; review consistency: 3.1/7; review freshness: 7.1/8; verified website: 13.5/15; confirmed irs record: 20.0/20; source corroboration: 5.0/5; Synthesis metadata: high (not part of numeric confidence) | P8: 8312026 | Q8: =IF(OR(ISBLANK(M8), ISBLANK(N8)), "", IF(N8 < Sheet3!$B$6, "Insufficient Reviews", IF(M8 >= Sheet3!$B$2, "Highly Reliable", IF(M8 >= Sheet3!$B$3, "Reliable", IF(M8 >= Sheet3!$B$4, "Mixed Reviews", "Low Reliability"))))) -> Highly Reliable
A9: =A8+1 -> 8 | B9: 4120 Patterson Ave, Baltimore, MD 21215 | C9: 39.355171 | D9: -76.704672 | E9: (410) 764-2266 | F9: Park West Health System | G9: Appointments are recommended and/or required. The center states it provides care regardless of ability to pay and offers free or low-cost care based on individual circumstances. (Evidence supports appointment-based intake and sliding-scale/low-cost options.) | H9: Monday: 9 AM to 5:30 PM; Tuesday: 9 AM to 5:30 PM; Wednesday: 9 AM to 5:30 PM; Thursday: 9 AM to 5:30 PM; Friday: 9 AM to 5:30 PM; Saturday: Closed; Sunday: Closed | I9: Physical & General Health Care | J9: A community-based medical clinic and federally qualified health center that provides primary and preventive medical care, pediatrics, behavioral health, and related services across multiple Park West locations in Northwest Baltimore. | K9: http://www.parkwestmed.org/ | L9: Google Maps reviewers repeatedly praise individual clinicians and some staff for good patient interactions and attentive providers. Recurring negative themes include difficulty scheduling or getting timely appointment responses, long waits and missed provider visits, billing or insurance handling problems, and concerns about medication management or care continuity. The newest reviews in the fetched sample emphasize those access and scheduling problems rather than contradicting them. | M9: 69.081243 | N9: 70.645769 | O9: accepted google identity: 14.2/15; review volume: 30.0/30; review consistency: 1.0/7; review freshness: 7.8/8; verified website: 14.2/15; confirmed irs record: 0.0/20; source corroboration: 3.3/5; Synthesis metadata: high (not part of numeric confidence) | P9: 8312026 | Q9: =IF(OR(ISBLANK(M9), ISBLANK(N9)), "", IF(N9 < Sheet3!$B$6, "Insufficient Reviews", IF(M9 >= Sheet3!$B$2, "Highly Reliable", IF(M9 >= Sheet3!$B$3, "Reliable", IF(M9 >= Sheet3!$B$4, "Mixed Reviews", "Low Reliability"))))) -> Mixed Reviews
A10: =A9+1 -> 9 | B10: 1501 W Saratoga St, Baltimore, MD 21223 | C10: 39.291894 | D10: -76.641619 | E10: (410) 383-8300 | F10: Total Health Care - Saratoga Health Center | G10: Open to all; accepts most insurance | H10: Monday: 8:30 AM to 7 PM; Tuesday: 8:30 AM to 7 PM; Wednesday: 8:30 AM to 7 PM; Thursday: 8:30 AM to 7 PM; Friday: 8:30 AM to 6 PM; Saturday: Closed; Sunday: Closed | I10: Physical & General Health Care | J10: A medical clinic / community health center providing general primary and outpatient medical care. The facility’s listing indicates on-site pharmacy services and behavioral health/counseling services. | K10: http://www.totalhealthcare.org/ | L10: Reviewers commonly praise the clinic’s staff and find the location convenient, reporting positive experiences with providers. Recurring complaints describe administrative problems — such as appointment redirections, delays or problems with deliveries and dental follow‑through, and occasional unexpected closures — which have led to some negative experiences. The owner has replied to some reviews; the most recent feedback includes positive reports but the mix of criticisms suggests service consistency can vary. | M10: 73.322945 | N10: 71.404651 | O10: accepted google identity: 14.2/15; review volume: 30.0/30; review consistency: 1.6/7; review freshness: 8.0/8; verified website: 14.2/15; confirmed irs record: 0.0/20; source corroboration: 3.3/5; Synthesis metadata: medium (not part of numeric confidence) | P10: 8312026 | Q10: =IF(OR(ISBLANK(M10), ISBLANK(N10)), "", IF(N10 < Sheet3!$B$6, "Insufficient Reviews", IF(M10 >= Sheet3!$B$2, "Highly Reliable", IF(M10 >= Sheet3!$B$3, "Reliable", IF(M10 >= Sheet3!$B$4, "Mixed Reviews", "Low Reliability"))))) -> Reliable
A11: =A10+1 -> 10 | B11: 5807 Harford Rd, Baltimore, MD 21214 | C11: 39.355368 | D11: -76.558075 | E11: (410) 444-2100 | F11: Harbel Community Organization | G11: Offers services to residents of Baltimore City and Baltimore County; homebuyers are advised to seek services from the housing counseling agency serving the area where they are most likely to purchase a home. Serves both adults and adolescents. (Access details and intake documentation requirements were not specified in the supplied evidence.) | H11: Monday: 9 AM to 7 PM; Tuesday: 9 AM to 7 PM; Wednesday: 9 AM to 7 PM; Thursday: 9 AM to 7 PM; Friday: 9 AM to 2 PM; Saturday: Closed; Sunday: Closed | I11: Housing & Shelter | J11: A neighborhood community organization that provides housing-related programs (housing counseling and homebuyer education/workshops), prevention and recovery services for substance use and mental health, and broader community relation/service activities serving the Northeast Baltimore area. | K11: http://www.harbel.org/ | L11: Google Maps reviewers most frequently praise educational homebuyer workshops and describe staff as helpful, professional, and patient; recent reviews are strongly positive and describe free, informative workshops. A minority of older reviews raise concerns about staff interactions and participant requirements for classes. Administrative records and the organization website corroborate the listed programs and identity. | M11: 78.837342 | N11: 92.494337 | O11: accepted google identity: 14.2/15; review volume: 30.0/30; review consistency: 1.4/7; review freshness: 7.6/8; verified website: 14.2/15; confirmed irs record: 20.0/20; source corroboration: 5.0/5; Synthesis metadata: high (not part of numeric confidence) | P11: 8312026 | Q11: =IF(OR(ISBLANK(M11), ISBLANK(N11)), "", IF(N11 < Sheet3!$B$6, "Insufficient Reviews", IF(M11 >= Sheet3!$B$2, "Highly Reliable", IF(M11 >= Sheet3!$B$3, "Reliable", IF(M11 >= Sheet3!$B$4, "Mixed Reviews", "Low Reliability"))))) -> Reliable
A12: =A11+1 -> 11 | B12: 3009 Greenmount Ave, Baltimore, MD 21218 | C12: 39.324853 | D12: -76.608877 | E12: (410) 547-9934 | F12: The Forge of The BIT Center | G12: Some programs (for example, cooking classes) require advance registration; sign-up information and program details are published on the organization's website. | H12: Monday: Closed; Tuesday: 10 AM to 5 PM; Wednesday: 10 AM to 5 PM; Thursday: 10 AM to 5 PM; Friday: 10 AM to 5 PM; Saturday: Closed; Sunday: Closed | I12: Food & Essential Needs | J12: A neighborhood community center providing food access and gastronomy education alongside cultural arts, youth empowerment, and workforce-development programs. | K12: http://www.thebitcenter.org/ | L12: Available reviewer feedback praises accommodating staff and homemade food offerings and specifically mentions community food provision and pasta made from scratch. The single provided review contains only positive remarks and does not raise operational concerns. The organization's official website and a confirmed registry record further corroborate the programs and contact details listed on the public map entry. | M12: 89.357004 | N12: 73.100765 | O12: accepted google identity: 14.2/15; review volume: 5.0/30; review consistency: 7.0/7; review freshness: 7.6/8; verified website: 14.2/15; confirmed irs record: 20.0/20; source corroboration: 5.0/5; Synthesis metadata: high (not part of numeric confidence) | P12: 8312026 | Q12: =IF(OR(ISBLANK(M12), ISBLANK(N12)), "", IF(N12 < Sheet3!$B$6, "Insufficient Reviews", IF(M12 >= Sheet3!$B$2, "Highly Reliable", IF(M12 >= Sheet3!$B$3, "Reliable", IF(M12 >= Sheet3!$B$4, "Mixed Reviews", "Low Reliability"))))) -> Highly Reliable
A13: =A12+1 -> 12 | B13: 3600 Clipper Mill Rd Ste 212, Baltimore, MD 21211 | C13: 39.330921 | D13: -76.642304 | E13: (443) 726-1318 | F13: LifeSpring Counseling | G13: Appointments are required/recommended; online scheduling available 24/7 and a dedicated staff member answers phones Monday–Friday during posted hours. The practice accepts insurance and advertises quick appointment availability (appointments often within about a week). Psychedelic‑assisted therapy (KAP) requires a preliminary consultation (free 15‑minute consult offered, contact by email per website). Services are offered both in‑person at the Baltimore office and via telehealth statewide in Maryland. | H13: Monday: 9 AM to 5 PM; Tuesday: 9 AM to 5 PM; Wednesday: 9 AM to 5 PM; Thursday: 9 AM to 5 PM; Friday: 9 AM to 5 PM; Saturday: Closed; Sunday: Closed | I13: Behavioral Health, Substance Use, & Crisis | J13: A Maryland counseling practice offering in-person and telehealth therapy, providing individual counseling for anxiety, depression, trauma/PTSD, and related concerns; the practice advertises specialized modalities including Brainspotting and psychedelic‑assisted therapy (KAP), and indicates it accepts insurance and schedules appointments quickly. | K13: http://lifespringcounseling.net/ | L13: Public reviewer comments emphasize compassionate, nurturing, and supportive clinicians; the most recent review echoes those positive themes. However, written review text is sparse and dated, so user-feedback evidence is limited and should be generalized cautiously. Non‑review corroborating sources (the Google business listing and the practice website) consistently show reachable website, posted hours, in‑person and telehealth service options, appointment requirements, and insurance acceptance. | M13: 67.437856 | N13: 51.939161 | O13: accepted google identity: 14.2/15; review volume: 12.0/30; review consistency: 7.0/7; review freshness: 1.2/8; verified website: 14.2/15; confirmed irs record: 0.0/20; source corroboration: 3.3/5; Synthesis metadata: high (not part of numeric confidence) | P13: 8312026 | Q13: =IF(OR(ISBLANK(M13), ISBLANK(N13)), "", IF(N13 < Sheet3!$B$6, "Insufficient Reviews", IF(M13 >= Sheet3!$B$2, "Highly Reliable", IF(M13 >= Sheet3!$B$3, "Reliable", IF(M13 >= Sheet3!$B$4, "Mixed Reviews", "Low Reliability"))))) -> Mixed Reviews
A14: =A13+1 -> 13 | B14: 5124 Greenwich Ave, Baltimore, MD 21229 | C14: 39.290394 | D14: -76.709523 | E14: (410) 433-5255 | F14: CarePoint Response | G14: Provides 24/7 access to crisis support (including via the 988 helpline). Residential and outpatient services accept Medicare, Medicaid, uninsured clients, and veterans. Provider referrals: be prepared to provide a face sheet and all clinical documentation (notes, reports, test results, exams). The site indicates referrals are accepted and that the organization follows up on referrals (website says follow-up within 24 hours). | H14: Monday: Open 24 hours; Tuesday: Open 24 hours; Wednesday: Open 24 hours; Thursday: Open 24 hours; Friday: Open 24 hours; Saturday: Open 24 hours; Sunday: Open 24 hours | I14: Behavioral Health, Substance Use, & Crisis | J14: A 24/7 crisis-response organization providing trauma-informed behavioral health and substance-use crisis services, including a 988 helpline backup, on-demand mobile response teams, short-term residential stabilization and a substance-use urgent care option, plus case management, care coordination, diversion programs, and training/outreach for partners. | K14: https://carepointresponse.org/ | L14: Public feedback is mixed. Several recent reviewers left high ratings without written comments, while multiple low-rated reviews include detailed complaints about residential conditions and frustration with housing voucher processes and case-management continuity. The organization’s website and its Google Business profile consistently describe 24/7 crisis services, residential and substance-use stabilization, mobile response, and case management, which corroborates the service types; however, reviewer text raises recurring concerns about facility upkeep and administrative delays. | M14: 65.560475 | N14: 56.801408 | O14: accepted google identity: 14.2/15; review volume: 18.0/30; review consistency: 0.0/7; review freshness: 7.0/8; verified website: 14.2/15; confirmed irs record: 0.0/20; source corroboration: 3.3/5; Synthesis metadata: high (not part of numeric confidence) | P14: 8312026 | Q14: =IF(OR(ISBLANK(M14), ISBLANK(N14)), "", IF(N14 < Sheet3!$B$6, "Insufficient Reviews", IF(M14 >= Sheet3!$B$2, "Highly Reliable", IF(M14 >= Sheet3!$B$3, "Reliable", IF(M14 >= Sheet3!$B$4, "Mixed Reviews", "Low Reliability"))))) -> Mixed Reviews
A15: =A14+1 -> 14 | B15: 400 S Bond St, Baltimore, MD 21231 | C15: 39.286352 | D15: -76.595716 | E15: (410) 732-1892 | F15: Beans & Bread | G15: Wheelchair accessible entrance and wheelchair accessible parking lot (Google Maps). Located within St Vincent De Paul (Google Maps). No verified, sitewide eligibility, intake, or documentation requirements were found in the available evidence. | H15: Monday: 9 AM to 2 PM; Tuesday: 9 AM to 2 PM; Wednesday: 9 AM to 2 PM; Thursday: 9 AM to 2 PM; Friday: 9 AM to 2 PM; Saturday: Closed; Sunday: Closed | I15: Food & Essential Needs | J15: A street‑level service site that provides on-site meals and food distribution and offers basic hygiene and support services (reviewers report showers, free laundry, and help establishing a mailing address). | K15: http://www.vincentbaltimore.org/get-help | L15: Google Maps reviewers commonly praise the quality of meals and the compassion of staff, and multiple recent reviewers specifically mention daily hot meals and available laundry and shower facilities. Recurring concerns in the reviews include complaints about cleanliness, restrictive on-site rules, and some reports of not receiving housing help or experiencing perceived discrimination. The newest reviews still highlight positive experiences around food and mailing/address assistance, so recent feedback continues the overall mixed-but-often-positive pattern. | M15: 74.210889 | N15: 70.344697 | O15: accepted google identity: 13.5/15; review volume: 30.0/30; review consistency: 2.1/7; review freshness: 7.9/8; verified website: 13.5/15; confirmed irs record: 0.0/20; source corroboration: 3.3/5; Synthesis metadata: high (not part of numeric confidence) | P15: 8312026 | Q15: =IF(OR(ISBLANK(M15), ISBLANK(N15)), "", IF(N15 < Sheet3!$B$6, "Insufficient Reviews", IF(M15 >= Sheet3!$B$2, "Highly Reliable", IF(M15 >= Sheet3!$B$3, "Reliable", IF(M15 >= Sheet3!$B$4, "Mixed Reviews", "Low Reliability"))))) -> Reliable
... A18: =A17+1 -> 17 | B18: 400 Cathedral St, Baltimore, MD 21201 | C18: 39.294555 | D18: -76.617217 | E18: (410) 396-5430 | F18: Enoch Pratt Free Library - Central Library | G18: Books by Mail: available to Baltimore City residents of all ages who are unable to visit the library due to a permanent or temporary disability. Book a Librarian: free 60-minute appointment available in-person, by phone, or via video (requires booking). Telephone reference is available during the Central Library's hours of operation. Deaf or hard of hearing customers may use Maryland Relay (#711 or 1-800-735-2258). Pratt Free Market is run at a different Pratt location (Southeast Anchor Library) and operates two days per week. | H18: Monday: 10 AM to 8 PM; Tuesday: 10 AM to 8 PM; Wednesday: 10 AM to 8 PM; Thursday: 10 AM to 8 PM; Friday: 10 AM to 5 PM; Saturday: 10 AM to 5 PM; Sunday: Closed | I18: Youth, Family, & General Support Services | J18: Enoch Pratt Free Library – Central is Baltimore’s main public library branch offering on-site book and media lending, reading and study spaces, public computers and internet access, research help and librarian appointments, meeting rooms, and a range of outreach and community-assistance programs and mobile services. | K18: https://www.prattlibrary.org/ | L18: Google reviewers commonly praise the Central Library’s renovated facility, large collection, quiet resourceful spaces, and helpful staff; recent reviews continue to reflect these positive themes. A minority of reviewers report service breakdowns such as missed or poorly followed-up appointments for assistance. Official sources (the library’s website and public records) corroborate that this branch is active and operating regular programs and services. | M18: 84.984086 | N18: 94.655732 | O18: accepted google identity: 14.2/15; review volume: 30.0/30; review consistency: 3.2/7; review freshness: 8.0/8; verified website: 14.2/15; confirmed irs record: 20.0/20; source corroboration: 5.0/5; Synthesis metadata: high (not part of numeric confidence) | P18: 8312026 | Q18: =IF(OR(ISBLANK(M18), ISBLANK(N18)), "", IF(N18 < Sheet3!$B$6, "Insufficient Reviews", IF(M18 >= Sheet3!$B$2, "Highly Reliable", IF(M18 >= Sheet3!$B$3, "Reliable", IF(M18 >= Sheet3!$B$4, "Mixed Reviews", "Low Reliability"))))) -> Highly Reliable
A19: =A18+1 -> 18 | B19: 101 W Mt Royal Ave, Baltimore, MD 21201 | C19: 39.305085 | D19: -76.61791 | E19: (410) 234-0023 | F19: Chana Helpline | H19: Monday: 9:00 am - 8:00 pm; Tuesday: 9:00 am - 8:00 pm; Wednesday: 9:00 am - 8:00 pm; Thursday: 9:00 am - 8:00 pm; Friday: 9:00 am - 4:00 pm; Saturday CLOSED; Sunday: 9:00 am - 12:00 pm | I19: Safety & Anti-Violence | J19: Provides support, advocacy, and educational services for people affected by intimate partner violence and domestic abuse, focusing on survivor support and related advocacy/education. | K19: http://chanabaltimore.org/ | L19: Available reviewer comments are strongly positive: reviewers describe the organization as knowledgeable, supportive, and active in advocacy and education around intimate partner violence/domestic abuse. There are no recurring complaints or negative themes in the provided review text, and the most recent review aligns with earlier praise. Public website content was not substantive, so reviewer feedback and the Google Maps category are the primary corroborating signals. | M19: 80.01054 | N19: 55.165885 | O19: accepted google identity: 14.2/15; review volume: 10.1/30; review consistency: 7.0/7; review freshness: 6.3/8; verified website: 14.2/15; confirmed irs record: 0.0/20; source corroboration: 3.3/5; Synthesis metadata: medium (not part of numeric confidence) | P19: 8312026 | Q19: =IF(OR(ISBLANK(M19), ISBLANK(N19)), "", IF(N19 < Sheet3!$B$6, "Insufficient Reviews", IF(M19 >= Sheet3!$B$2, "Highly Reliable", IF(M19 >= Sheet3!$B$3, "Reliable", IF(M19 >= Sheet3!$B$4, "Mixed Reviews", "Low Reliability"))))) -> Reliable
A20: =A19+1 -> 19 | B20: 8503 Lasalle Rd, Towson, MD 21286 | C20: 39.393727 | D20: -76.5769 | E20: (410) 377-8111 | F20: Turnaround Inc | G20: Services are for survivors of intimate partner violence, sexual violence, and human trafficking in Baltimore County and Baltimore City; human trafficking services extend to Howard County. A 24/7 crisis helpline and crisis text line are published. Some programs note appointments are required or recommended; certain programs (e.g., abuser-intervention) are fee-based while legal services are described as free consultations/representation. (Sources: evidence_id 6 — official website; evidence_id 4 — Google Maps listing.) | H20: Monday: 9 AM to 5 PM; Tuesday: 9 AM to 5 PM; Wednesday: 9 AM to 5 PM; Thursday: 9 AM to 5 PM; Friday: 9 AM to 5 PM; Saturday: Closed; Sunday: Closed | I20: Safety & Anti-Violence | J20: TurnAround, Inc. is a Baltimore-area violence survivor support organization that operates a crisis helpline/text line and provides trauma-informed services including therapy, advocacy and resource navigation, legal assistance, an abuser-intervention program, and community training and outreach. | K20: http://www.turnaroundinc.org/ | L20: Reviewer feedback shows a split pattern: some survivors report receiving immediate, tangible help (accommodations, transportation, food), while many recent reviewers describe problems with responsiveness, follow-through, and unprofessional communications when seeking help or shelter. Several reviews raise safety- and trust-related concerns tied to delayed or missing support, and the latest reviews continue to emphasize those negative experiences. Owner/agency responses to the public reviews are not present in the provided sample. | M20: 55.093588 | N20: 88.884948 | O20: accepted google identity: 14.2/15; review volume: 26.5/30; review consistency: 2.6/7; review freshness: 6.3/8; verified website: 14.2/15; confirmed irs record: 20.0/20; source corroboration: 5.0/5; Synthesis metadata: high (not part of numeric confidence) | P20: 8312026 | Q20: =IF(OR(ISBLANK(M20), ISBLANK(N20)), "", IF(N20 < Sheet3!$B$6, "Insufficient Reviews", IF(M20 >= Sheet3!$B$2, "Highly Reliable", IF(M20 >= Sheet3!$B$3, "Reliable", IF(M20 >= Sheet3!$B$4, "Mixed Reviews", "Low Reliability"))))) -> Low Reliability
A21: =A20+1 -> 20 | B21: 915 Sterrett St, Baltimore, MD 21230 | C21: 39.281118 | D21: -76.626992 | E21: (667) 600-3776 | F21: Catholic Charities Head Start of Baltimore City | I21: Youth, Family, & General Support Services | J21: A Head Start center operated by Catholic Charities located in Baltimore that provides early childhood / Head Start daycare and related program activities at the Head Start of Baltimore City site. The presence of this Head Start location is corroborated by the Google Maps listing and the organization’s official website. | K21: http://www.catholiccharities-md.org/ | L21: The Google Maps listing and the organization’s official website both corroborate the existence of a Head Start location at this address, and the website is reachable. Review text was not available for analysis, so user feedback and on-the-ground experience could not be assessed. The listing does not publish structured opening hours, limiting scheduling details. | M21: 72 | N21: 40.724992 | O21: accepted google identity: 14.2/15; review volume: 8.9/30; review consistency: 0.0/7; review freshness: 0.0/8; verified website: 14.2/15; confirmed irs record: 0.0/20; source corroboration: 3.3/5; Synthesis metadata: medium (not part of numeric confidence) | P21: 8312026 | Q21: =IF(OR(ISBLANK(M21), ISBLANK(N21)), "", IF(N21 < Sheet3!$B$6, "Insufficient Reviews", IF(M21 >= Sheet3!$B$2, "Highly Reliable", IF(M21 >= Sheet3!$B$3, "Reliable", IF(M21 >= Sheet3!$B$4, "Mixed Reviews", "Low Reliability"))))) -> Reliable
A22: =A21+1 -> 21 | B22: A. Hoen and Co., 2101 E Biddle St Ste 1100, Baltimore, MD 21213 | C22: 39.304115 | D22: -76.587923 | E22: (410) 261-3500 | F22: Strong City Baltimore | H22: Monday: 9 AM to 5 PM; Tuesday: 9 AM to 5 PM; Wednesday: 9 AM to 5 PM; Thursday: 9 AM to 5 PM; Friday: 9 AM to 5 PM; Saturday: Closed; Sunday: Closed | I22: Employment, Training, & Education | J22: A physical education center listed in Baltimore that appears to offer in-person learning programs at this address. | L22: Google Maps listing and hours are available for a physical location, but independent corroboration is limited. Public review text is sparse and mixed: the sampled reviews include a recent positive, text-free rating and an earlier review that specifically complained the telephone number did not work. Because reviews and other corroborating sources are limited and the organization’s website could not be verified, program details and access procedures are not well-documented from the available evidence. | M22: 62.717292 | N22: 35.060608 | O22: accepted google identity: 14.2/15; review volume: 15.1/30; review consistency: 0.0/7; review freshness: 4.0/8; verified website: 0.0/15; confirmed irs record: 0.0/20; source corroboration: 1.7/5; Synthesis metadata: medium (not part of numeric confidence) | P22: 8312026 | Q22: =IF(OR(ISBLANK(M22), ISBLANK(N22)), "", IF(N22 < Sheet3!$B$6, "Insufficient Reviews", IF(M22 >= Sheet3!$B$2, "Highly Reliable", IF(M22 >= Sheet3!$B$3, "Reliable", IF(M22 >= Sheet3!$B$4, "Mixed Reviews", "Low Reliability"))))) -> Insufficient Reviews
A23: =A22+1 -> 22 | B23: 620 Fallsway, Baltimore, MD 21202 | C23: 39.297412 | D23: -76.610586 | E23: (667) 600-3230 | F23: Weinberg Housing and Resource Center | G23: Open to adult men and women experiencing homelessness. All prospective residents must contact the Mayor's Office of Homeless Services Coordinated Entry Line at 443-984-9540 to request shelter referrals between 9:30am and 9:00pm (Coordinated Entry intake required). | H23: Monday: 9 AM to 5 PM; Tuesday: 9 AM to 5 PM; Wednesday: 9 AM to 5 PM; Thursday: Closed; Friday: 9 AM to 5 PM; Saturday: Closed; Sunday: 9 AM to 5 PM | I23: Housing & Shelter | J23: A low-barrier emergency shelter and homeless-services site that provides short-term emergency shelter for adults and connects residents to case management and housing-placement supports. The program also offers on-site basic supports such as meals, laundry, client transportation, workforce development training, and referrals to behavioral-health services. | K23: http://www.cc-md.org/WHRC | L23: Public reviewer feedback contains both strong praise for the center’s resources and staff support and recurring complaints about safety and cleanliness. Positive comments emphasize plentiful resources and staff who help residents seeking stability; recurring negatives raise bed‑bug reports, theft/safety concerns, and instances of unsympathetic or unhelpful intake interactions. The most recent reviews tilt toward those negative issues, and there are no visible owner responses in the public review thread. | M23: 70.419503 | N23: 71.606093 | O23: accepted google identity: 14.2/15; review volume: 30.0/30; review consistency: 1.8/7; review freshness: 8.0/8; verified website: 14.2/15; confirmed irs record: 0.0/20; source corroboration: 3.3/5; Synthesis metadata: high (not part of numeric confidence) | P23: 8312026 | Q23: =IF(OR(ISBLANK(M23), ISBLANK(N23)), "", IF(N23 < Sheet3!$B$6, "Insufficient Reviews", IF(M23 >= Sheet3!$B$2, "Highly Reliable", IF(M23 >= Sheet3!$B$3, "Reliable", IF(M23 >= Sheet3!$B$4, "Mixed Reviews", "Low Reliability"))))) -> Reliable
A24: =A23+1 -> 23 | B24: 2401 Liberty Heights Ave #302, Baltimore, MD 21215 | C24: 39.316766 | D24: -76.654108 | E24: (410) 396-7873 | F24: Northwest Career Center (Background Friendly Job Center) | G24: Stated eligibility: services for adult Baltimore City residents. No appointment required (drop‑in). The official site provides a form to request/receive services (online intake option). | H24: Monday: 8:30 AM to 4:30 PM; Tuesday: 8:30 AM to 4:30 PM; Wednesday: 8:30 AM to 4:30 PM; Thursday: 8:30 AM to 4:30 PM; Friday: 8:30 AM to 4:30 PM; Saturday: Closed; Sunday: Closed | I24: Employment, Training, & Education | J24: A city-run career center that provides access to background‑friendly jobs, workforce training, and job‑search supports (including resume and placement help). The listing and site indicate services are offered as a physical, drop‑in location. | K24: https://moed.baltimorecity.gov/northwest-baltimore-career-center-contact | L24: User reviews describe staff who can be helpful and willing to assist, especially with resume and job search needs, but also repeatedly note long waits, limited daily capacity, and some negative experiences around phone information or perceived bias in access. Several recent reviews are negative, indicating that service experiences remain mixed; the listing owner has responded to some feedback. | M24: 67.855821 | N24: 70.598528 | O24: accepted google identity: 14.2/15; review volume: 30.0/30; review consistency: 1.0/7; review freshness: 7.8/8; verified website: 14.2/15; confirmed irs record: 0.0/20; source corroboration: 3.3/5; Synthesis metadata: medium (not part of numeric confidence) | P24: 8312026 | Q24: =IF(OR(ISBLANK(M24), ISBLANK(N24)), "", IF(N24 < Sheet3!$B$6, "Insufficient Reviews", IF(M24 >= Sheet3!$B$2, "Highly Reliable", IF(M24 >= Sheet3!$B$3, "Reliable", IF(M24 >= Sheet3!$B$4, "Mixed Reviews", "Low Reliability"))))) -> Mixed Reviews
A25: =A24+1 -> 24 | B25: 1410 Bush St, Baltimore, MD 21230 | C25: 39.27629 | D25: -76.635498 | E25: (410) 396-1052 | F25: Employment Connection Center | G25: Website hosts a form to request services (online intake). A Google Maps review reports the center referring people to a different site based on zip code; this user report suggests there may be geographic-eligibility or service-area rules reported by staff, but that restriction is documented only in a reviewer comment. | H25: Monday: 8:30 AM to 4:30 PM; Tuesday: 8:30 AM to 4:30 PM; Wednesday: 8:30 AM to 4:30 PM; Thursday: 8:30 AM to 4:30 PM; Friday: 8:30 AM to 4:30 PM; Saturday: Closed; Sunday: Closed | I25: Employment, Training, & Education | J25: A physical Employment Connection Center operated through Baltimore City that provides in-person employment and training-related services for people seeking work, with an online intake form to request services. | K25: https://moed.baltimorecity.gov/south-baltimore-employment-connections-center | L25: Google Maps reviewers most commonly describe helpful staff, counselors, and the center being a useful resource for finding jobs or training. Recurring negative reports say staff have sometimes refused entry or sent people to other locations and that posted hours were not always honored; the newest reviews echo those access and hours complaints. The listing owner has responded to multiple reviewer complaints, indicating some owner responsiveness to feedback. | M25: 71.683008 | N25: 60.928063 | O25: accepted google identity: 13.3/15; review volume: 24.2/30; review consistency: 0.9/7; review freshness: 5.8/8; verified website: 13.3/15; confirmed irs record: 0.0/20; source corroboration: 3.3/5; Synthesis metadata: high (not part of numeric confidence) | P25: 8312026 | Q25: =IF(OR(ISBLANK(M25), ISBLANK(N25)), "", IF(N25 < Sheet3!$B$6, "Insufficient Reviews", IF(M25 >= Sheet3!$B$2, "Highly Reliable", IF(M25 >= Sheet3!$B$3, "Reliable", IF(M25 >= Sheet3!$B$4, "Mixed Reviews", "Low Reliability"))))) -> Reliable
A26: =A25+1 -> 25 | B26: 3001 E Madison St, Baltimore, MD 21205 | C26: 39.299925 | D26: -76.575042 | E26: (410) 396-9030 | F26: Eastside Career Center | G26: Site materials state services are offered to adult Baltimore City residents; no appointment is required and walk-ins are welcome. The official site affirms equal-opportunity nondiscrimination and invites customers to request auxiliary aids or interpreter services as needed. | H26: Monday: 8:30 AM to 4:30 PM; Tuesday: 8:30 AM to 4:30 PM; Wednesday: 8:30 AM to 4:30 PM; Thursday: 8:30 AM to 4:30 PM; Friday: 8:30 AM to 4:30 PM; Saturday: Closed; Sunday: Closed | I26: Employment, Training, & Education | J26: A Baltimore City American Job Center location that provides in-person help with job search and workforce services including career counseling, connections to training programs, résumé help, workshops, and access to computers and basic office equipment. Employer-facing business services are also listed on the official site. | K26: https://www.labor.maryland.gov/county/bacity/ | L26: Reviewers commonly report approachable and helpful staff and that the center provides useful resources for finding work and training. Recurring concerns in reviews include long waits, inconsistent front-desk experiences, occasional early closing, and frustration that some in-person assistance directs users back to web resources. Recent reviews include positive comments about staff and job help alongside some ongoing complaints, and center staff have posted responses to several critical reviews. | M26: 74.801744 | N26: 70.06193 | O26: accepted google identity: 14.2/15; review volume: 30.0/30; review consistency: 1.1/7; review freshness: 7.2/8; verified website: 14.2/15; confirmed irs record: 0.0/20; source corroboration: 3.3/5; Synthesis metadata: high (not part of numeric confidence) | P26: 8312026 | Q26: =IF(OR(ISBLANK(M26), ISBLANK(N26)), "", IF(N26 < Sheet3!$B$6, "Insufficient Reviews", IF(M26 >= Sheet3!$B$2, "Highly Reliable", IF(M26 >= Sheet3!$B$3, "Reliable", IF(M26 >= Sheet3!$B$4, "Mixed Reviews", "Low Reliability"))))) -> Reliable
A27: =A26+1 -> 26 | B27: 2305 N Charles St, Baltimore, MD 21218 | C27: 39.314737 | D27: -76.616788 | E27: (410) 230-0630 | F27: Maryland New Directions Inc | G27: Programs are offered at no cost. Enrollment requires completion of the Career Focus (job-readiness) step prior to industry-specific program enrollment. Services are targeted to Baltimore-area residents age 18 and older; the organization states it does not discriminate in program administration. | H27: Monday: 8:30 AM to 4:30 PM; Tuesday: 8:30 AM to 4:30 PM; Wednesday: 8:30 AM to 4:30 PM; Thursday: 8:30 AM to 4:30 PM; Friday: 8:30 AM to 4:30 PM; Saturday: Closed; Sunday: Closed | I27: Employment, Training, & Education | J27: Maryland New Directions provides no-cost employment coaching and career-training programs for adults, including a required job-readiness course followed by industry-specific training that leads to industry-recognized credentials (examples cited include forklift and OSHA training and commercial driver permit preparation). The organization also supports resume-building, soft-skill development, and employer connections to help participants find work. | K27: http://www.mdnewdirections.org/ | L27: Public Google Maps reviewers consistently praise staff as helpful and supportive, and they report positive experiences with the training, coaching, and credential preparation (reviews frequently mention resume help, forklift certification, and job-readiness). Owner responses are present on reviews, and recent review text remains strongly positive, indicating ongoing consistent performance. The listing and an accepted official website snapshot both corroborate program details, and registry/filing signals further support the organization’s active identity. | M27: 86.843867 | N27: 95.549511 | O27: accepted google identity: 14.2/15; review volume: 30.0/30; review consistency: 4.2/7; review freshness: 7.8/8; verified website: 14.2/15; confirmed irs record: 20.0/20; source corroboration: 5.0/5; Synthesis metadata: high (not part of numeric confidence) | P27: 8312026 | Q27: =IF(OR(ISBLANK(M27), ISBLANK(N27)), "", IF(N27 < Sheet3!$B$6, "Insufficient Reviews", IF(M27 >= Sheet3!$B$2, "Highly Reliable", IF(M27 >= Sheet3!$B$3, "Reliable", IF(M27 >= Sheet3!$B$4, "Mixed Reviews", "Low Reliability"))))) -> Highly Reliable
A28: =A27+1 -> 27 | B28: 201 N Charles St, Baltimore, MD 21201 | C28: 39.291343 | D28: -76.614754 | E28: (410) 234-8040 | F28: Job Opportunities Task Force | G28: BetterU Construction Training is for Baltimore residents and requires a high school diploma or GED. The facility listing indicates a wheelchair-accessible entrance and wheelchair-accessible parking. | H28: Monday: 9 AM to 5 PM; Tuesday: 9 AM to 5 PM; Wednesday: 9 AM to 5 PM; Thursday: 9 AM to 5 PM; Friday: 9 AM to 5 PM; Saturday: Closed; Sunday: Closed | I28: Employment, Training, & Education | J28: Provides workforce-development and training programs aimed at reducing educational and employment barriers for low-wage workers. The organization operates BetterU Construction Training, a 14-week pre-apprenticeship that covers entry-level plumbing, carpentry, and electrical skills. | K28: http://www.jotf.org/ | L28: Public review text is very sparse and provides little or no written feedback, so reviewer themes are not discernible. The Google Maps listing includes a program description, phone number, structured hours, and accessibility details, but the organization’s website currently returns an error page. Because independent corroboration is limited and on-site web content is unavailable, the available information should be treated as only moderately verified. | M28: 73.366238 | N28: 50.677918 | O28: accepted google identity: 14.2/15; review volume: 8.9/30; review consistency: 7.0/7; review freshness: 3.0/8; verified website: 14.2/15; confirmed irs record: 0.0/20; source corroboration: 3.3/5; Synthesis metadata: medium (not part of numeric confidence) | P28: 8312026 | Q28: =IF(OR(ISBLANK(M28), ISBLANK(N28)), "", IF(N28 < Sheet3!$B$6, "Insufficient Reviews", IF(M28 >= Sheet3!$B$2, "Highly Reliable", IF(M28 >= Sheet3!$B$3, "Reliable", IF(M28 >= Sheet3!$B$4, "Mixed Reviews", "Low Reliability"))))) -> Reliable
A29: =A28+1 -> 28 | B29: 898 Airport Park Rd, Glen Burnie, MD 21061 | C29: 39.173685 | D29: -76.64452 | E29: (410) 242-9674 | F29: Vehicles for Change Corporate Office | G29: Keys to Independence program is described as providing affordable vehicles to low-income families. Full Circle Training enrolls justice-impacted individuals and others facing employment barriers. Vehicle awards and training appear to require an application and may involve a waiting period or eligibility review. (All access requirements are stated on the organization website and Google listing.) | H29: Monday: 8 AM to 5 PM; Tuesday: 8 AM to 5 PM; Wednesday: 8 AM to 5 PM; Thursday: 8 AM to 5 PM; Friday: 8 AM to 5 PM; Saturday: Closed; Sunday: Closed | I29: Youth, Family, & General Support Services | J29: Vehicles for Change operates vehicle-donation and resale programs that fund vehicle awards to low-income families, runs hands-on automotive workforce training (Full Circle Auto Training and VR training), and operates community auto-repair centers that support its mission. | K29: http://vehiclesforchange.org/ | L29: Reviewers commonly praise staff helpfulness, a smooth donation process, and positive experiences with the organization’s repair and training programs. Recurring concerns in the reviews center on slow or unclear communication about vehicle-award applications and waiting times. Owner responses to reviews are frequent, and recent reviews in the sample trend toward positive feedback; the organization’s IRS and website records corroborate its identity and programs. | M29: 76.062767 | N29: 90.856813 | O29: accepted google identity: 14.2/15; review volume: 30.0/30; review consistency: 0.7/7; review freshness: 6.7/8; verified website: 14.2/15; confirmed irs record: 20.0/20; source corroboration: 5.0/5; Synthesis metadata: high (not part of numeric confidence) | P29: 8312026 | Q29: =IF(OR(ISBLANK(M29), ISBLANK(N29)), "", IF(N29 < Sheet3!$B$6, "Insufficient Reviews", IF(M29 >= Sheet3!$B$2, "Highly Reliable", IF(M29 >= Sheet3!$B$3, "Reliable", IF(M29 >= Sheet3!$B$4, "Mixed Reviews", "Low Reliability"))))) -> Reliable
A30: =A29+1 -> 29 | B30: 800 W 36th St, Baltimore, MD 21211 | C30: 39.331505 | D30: -76.629766 | E30: (443) 402-5828 | F30: St. Luke's Church on the Avenue | G30: The Avenue Drop-In is conducted by a harm-reduction partner and runs currently on Fridays from 10:00am–11:00am; participants may receive services such as syringe exchange, hygiene supplies, treatment referrals, Narcan training/distribution, and a takeaway hot lunch. Participants of the drop-in are eligible for $25 vouchers to the Lost & Found Thrift Shop. The thrift shop accepts donations during its operating hours. (All access details supported by website: evidence_id 44; additional site accessibility / amenities noted on Google Maps: evidence_id 42.) | H30: Avenue Drop-In: Every Friday, 10:00am–11:00am. Gathering of Holy Communion (in person): Sunday mornings, 10:00am. Benedictine Morning Prayer: Monday–Friday, 7:30am. (All times taken from the organization website: evidence_id 44.) | I30: Food & Essential Needs | J30: St. Luke’s Church on the Avenue operates a neighborhood church and community site that hosts a thrift shop, a weekly drop-in run with a harm-reduction partner (including syringe exchange, hygiene supplies, naloxone training/distribution, referrals), a community garden, and periodic food distribution/hot lunch take-away. | K30: https://www.churchontheavenuehampden.org/ | L30: Recent Google Maps reviews consistently describe the location as a positive community space and explicitly praise its food distribution and related community programs. Reviewers' comments emphasize effective food distribution and an active neighborhood role; there are no recurring complaints evident in the recent sample. The most recent reviews continue the same positive themes, suggesting consistent experiences over time. | M30: 80.57803 | N30: 67.685292 | O30: accepted google identity: 14.2/15; review volume: 22.3/30; review consistency: 5.6/7; review freshness: 8.0/8; verified website: 14.2/15; confirmed irs record: 0.0/20; source corroboration: 3.3/5; Synthesis metadata: high (not part of numeric confidence) | P30: 8312026 | Q30: =IF(OR(ISBLANK(M30), ISBLANK(N30)), "", IF(N30 < Sheet3!$B$6, "Insufficient Reviews", IF(M30 >= Sheet3!$B$2, "Highly Reliable", IF(M30 >= Sheet3!$B$3, "Reliable", IF(M30 >= Sheet3!$B$4, "Mixed Reviews", "Low Reliability"))))) -> Reliable
A31: =A30+1 -> 30 | B31: 2631 Huntingdon Ave, Baltimore, MD 21211 | C31: 39.31976 | D31: -76.621675 | E31: (410) 929-3688 | F31: Church of the Guardian Angel | G31: Reviewers state the Wednesday food pantry is available “to anyone in need.” Review text also describes school supplies and holiday gifts provided to neighborhood children. Some reviewers recalled past limits on non-neighborhood attendees but later reviews indicate the church accepts visitors from outside the immediate neighborhood. | H31: Monday: Closed; Tuesday: Closed; Wednesday: 9 to 10 AM; Thursday: Closed; Friday: Closed; Saturday: Closed; Sunday: 10 to 11 AM | I31: Food & Essential Needs | J31: A neighborhood Episcopal church that holds regular Sunday worship (including a Spanish-language mass) and operates community support activities; reviewers report a weekly Wednesday morning food pantry and distributions of school supplies and holiday gifts for neighborhood children. | K31: https://www.facebook.com/Church-of-the-Guardian-Angel-259556444135884/ | L31: Google Maps reviewers consistently describe the congregation as warm, friendly, and welcoming and report active community supports such as a Wednesday food pantry and distributions of school supplies and holiday gifts. A few reviewers recalled an earlier period with restrictive attendance practices, but more recent reviews emphasize renewed openness and positive interactions with current staff. Review feedback is uniformly positive and the newest reviews continue that pattern. | M31: 85.407938 | N31: 85.309197 | O31: accepted google identity: 13.5/15; review volume: 21.4/30; review consistency: 7.0/7; review freshness: 4.9/8; verified website: 13.5/15; confirmed irs record: 20.0/20; source corroboration: 5.0/5; Synthesis metadata: high (not part of numeric confidence) | P31: 8312026 | Q31: =IF(OR(ISBLANK(M31), ISBLANK(N31)), "", IF(N31 < Sheet3!$B$6, "Insufficient Reviews", IF(M31 >= Sheet3!$B$2, "Highly Reliable", IF(M31 >= Sheet3!$B$3, "Reliable", IF(M31 >= Sheet3!$B$4, "Mixed Reviews", "Low Reliability"))))) -> Highly Reliable
A32: =A31+1 -> 31 | B32: 5353 Park Heights Ave, Baltimore, MD 21215 | C32: 39.350375 | D32: -76.680453 | E32: (410) 664-0907 | F32: Dayspring Inc. | G32: Open to community; program-specific | H32: Sun worship; weekly activities | I32: Youth, Family, & General Support Services | J32: Operates locally based programs, events, and resources focused on children and families, and offers volunteer opportunities and program registration for community participants. | K32: http://dayspringinc.org/ | L32: Public review feedback is unavailable: the Google Maps listing has no public reviews and no fetched review text to indicate user experiences. The organization has a verified website and a corroborating Google Maps listing, and archived snapshots show the site has been active in recent years, which together support the organization’s online presence and program descriptions. An IRS Business Master File match indicates a recent 2024 filing, further supporting ongoing organizational activity. Because there are no public reviews, judgments about service quality, consistency, or client experience cannot be drawn from review text. | M32: 10.5 | N32: 31.833333 | O32: accepted google identity: 14.2/15; review volume: 0.0/30; review consistency: 0.0/7; review freshness: 0.0/8; verified website: 14.2/15; confirmed irs record: 0.0/20; source corroboration: 3.3/5; Synthesis metadata: medium (not part of numeric confidence) | P32: 8312026 | Q32: =IF(OR(ISBLANK(M32), ISBLANK(N32)), "", IF(N32 < Sheet3!$B$6, "Insufficient Reviews", IF(M32 >= Sheet3!$B$2, "Highly Reliable", IF(M32 >= Sheet3!$B$3, "Reliable", IF(M32 >= Sheet3!$B$4, "Mixed Reviews", "Low Reliability"))))) -> Insufficient Reviews
A33: =A32+1 -> 32 | B33: 575 S Charles St Unit 500, Baltimore, MD 21201 | C33: 39.282697 | D33: -76.614103 | E33: (410) 528-8006 | F33: CASH Campaign of Maryland | G33: Targeted to low- to moderate-income individuals and families in Baltimore and across Maryland. Appointment scheduling is used for service delivery (reviewer comments and listing tags indicate appointments). Wheelchair-accessible entrance noted on the listing. | H33: Monday: 9 AM to 5 PM; Tuesday: 9 AM to 5 PM; Wednesday: 9 AM to 5 PM; Thursday: 9 AM to 5 PM; Friday: 9 AM to 5 PM; Saturday: Closed; Sunday: Closed | I33: Youth, Family, & General Support Services | J33: Provides tax preparation and filing assistance along with programs aimed at economic advancement for low- to moderate-income individuals and families in Baltimore and Maryland. Services are delivered in person at a physical location. | K33: http://www.cashmd.org/ | L33: Google Maps reviewers repeatedly praise staff as professional, personable, knowledgeable, and thorough when providing tax help; many recent reviews describe positive, helpful interactions. Recurring concerns are limited but include a number of low-rated entries with little or no explanatory text, and at least one reviewer who signaled unresolved issues. The listing’s owner is responsive in replies, and the most recent reviews remain largely positive. | M33: 72.478342 | N33: 94.496543 | O33: accepted google identity: 14.2/15; review volume: 30.0/30; review consistency: 4.1/7; review freshness: 6.9/8; verified website: 14.2/15; confirmed irs record: 20.0/20; source corroboration: 5.0/5; Synthesis metadata: high (not part of numeric confidence) | P33: 8312026 | Q33: =IF(OR(ISBLANK(M33), ISBLANK(N33)), "", IF(N33 < Sheet3!$B$6, "Insufficient Reviews", IF(M33 >= Sheet3!$B$2, "Highly Reliable", IF(M33 >= Sheet3!$B$3, "Reliable", IF(M33 >= Sheet3!$B$4, "Mixed Reviews", "Low Reliability"))))) -> Reliable
A34: =A33+1 -> 33 | B34: 2200 Halethorpe Farms Rd, Baltimore, MD 21227 | C34: 39.2242 | D34: -76.685386 | E34: (410) 737-8282 | F34: Maryland Food Bank | G34: Primary access is via partner organizations: use the Maryland Food Bank 'Find Food' tool to locate local partner pantries and contact the partner before visiting to confirm hours, eligibility, and distribution procedures. SNAP assistance is available via the phone/email contacts provided on the site. Do not assume walk-in grocery pickup or meal-service at the main distribution site without confirming with a partner. | H34: Monday: 8 AM to 4:30 PM; Tuesday: 8 AM to 4:30 PM; Wednesday: 8 AM to 4:30 PM; Thursday: 8 AM to 4:30 PM; Friday: 8 AM to 4:30 PM; Saturday: Closed; Sunday: Closed | I34: Food & Essential Needs | J34: Maryland Food Bank operates a statewide food-distribution network and provides tools and programs to connect people in Maryland with food assistance. Their site offers a searchable ‘Find Food’ tool to locate partner pantries, and the organization accepts donations and recruits volunteers; they also publish workforce-development programs and SNAP assistance contact options. | K34: http://www.mdfoodbank.org/ | L34: Google Maps reviewers commonly praise helpful and friendly staff, quick service, and a clean, well-maintained facility; several recent reviews continue that positive trend. A small number of reviews report negative or mixed experiences, indicating occasional service or experience issues for some visitors. The organization’s official website and archival snapshots corroborate the presence of a statewide partner network, donation and volunteer channels, and tools (like the Find Food search) to locate partner pantries. | M34: 81.540461 | N34: 72.84847 | O34: accepted google identity: 14.2/15; review volume: 30.0/30; review consistency: 3.0/7; review freshness: 8.0/8; verified website: 14.2/15; confirmed irs record: 0.0/20; source corroboration: 3.3/5; Synthesis metadata: high (not part of numeric confidence) | P34: 8312026 | Q34: =IF(OR(ISBLANK(M34), ISBLANK(N34)), "", IF(N34 < Sheet3!$B$6, "Insufficient Reviews", IF(M34 >= Sheet3!$B$2, "Highly Reliable", IF(M34 >= Sheet3!$B$3, "Reliable", IF(M34 >= Sheet3!$B$4, "Mixed Reviews", "Low Reliability"))))) -> Reliable
A35: =A34+1 -> 34 | B35: 725 Fallsway, Baltimore, MD 21202 | C35: 39.298209 | D35: -76.610296 | E35: (667) 600-3400 | F35: Our Daily Bread Employment Center | G35: Low-to-moderate income households | H35: Monday: 9 AM to 4 PM; Tuesday: 9 AM to 4 PM; Wednesday: 9 AM to 4 PM; Thursday: 9 AM to 4 PM; Friday: 9 AM to 4 PM; Saturday: Closed; Sunday: Closed | I35: Employment, Training, & Education | J35: According to the organization’s website and Google Maps listing and reviews, the site provides workforce-development and job-readiness services (including job coaching and training) and is reported by users to distribute food/meals and basic supports to people in need. | K35: http://www.catholiccharities-md.org/ | L35: Google Maps reviews are plentiful and consistently praise kind staff, food support, and help with finding work or training; several reviewers specifically mention meals, job coaches, and computer training. Negative or mixed feedback is minimal in the sampled reviews and the most recent reviews continue the same positive themes. The organization’s website also lists workforce and training programs, which aligns with the user reviews. | M35: 77.617763 | N35: 69.673186 | O35: accepted google identity: 13.5/15; review volume: 30.0/30; review consistency: 3.0/7; review freshness: 6.3/8; verified website: 13.5/15; confirmed irs record: 0.0/20; source corroboration: 3.3/5; Synthesis metadata: high (not part of numeric confidence) | P35: 8312026 | Q35: =IF(OR(ISBLANK(M35), ISBLANK(N35)), "", IF(N35 < Sheet3!$B$6, "Insufficient Reviews", IF(M35 >= Sheet3!$B$2, "Highly Reliable", IF(M35 >= Sheet3!$B$3, "Reliable", IF(M35 >= Sheet3!$B$4, "Mixed Reviews", "Low Reliability"))))) -> Reliable
A36: =A35+1 -> 35 | B36: 901 N Milton Ave, Baltimore, MD 21205 | C36: 39.30143 | D36: -76.582266 | E36: (410) 327-3420 | F36: Moveable Feast | G36: Medically tailored meals are provided via referral from a medical professional or a healthcare plan; client information should be sent to the client services contact rather than the public contact form (per site guidance). | I36: Food & Essential Needs | J36: Moveable Feast prepares and delivers medically tailored meals and provides nutrition education to people in Maryland living with serious or chronic illnesses; the organization also coordinates volunteer opportunities and meal delivery operations from a physical food-distribution center in Baltimore. | K36: http://www.mfeast.org/ | L36: Google reviewers frequently praise Moveable Feast as well organized, note strong volunteer engagement, and commend the quality of the food and the organization’s mission. Recurring negative feedback centers on delivery logistics and timing (for example, complaints about strict drop-off times and not leaving deliveries at the door). The most recent reviews remain predominantly positive while still reflecting the occasional delivery-related complaint that appears consistent over time. | M36: 81.580575 | N36: 93.341198 | O36: accepted google identity: 14.2/15; review volume: 30.0/30; review consistency: 1.9/7; review freshness: 8.0/8; verified website: 14.2/15; confirmed irs record: 20.0/20; source corroboration: 5.0/5; Synthesis metadata: high (not part of numeric confidence) | P36: 8312026 | Q36: =IF(OR(ISBLANK(M36), ISBLANK(N36)), "", IF(N36 < Sheet3!$B$6, "Insufficient Reviews", IF(M36 >= Sheet3!$B$2, "Highly Reliable", IF(M36 >= Sheet3!$B$3, "Reliable", IF(M36 >= Sheet3!$B$4, "Mixed Reviews", "Low Reliability"))))) -> Reliable
A37: =A36+1 -> 36 | B37: 101 W 23rd St, Baltimore, MD 21218 | C37: 39.314823 | D37: -76.618676 | E37: (410) 467-5340 | F37: Franciscan Center | G37: Some programs require client registration with the Center (and with partner agencies for certain services). Baby-item distributions require registration and clients may be asked for testimonials/photos; DSS food boxes require enrollment with the Center, DHS, and Link2Feed. Eviction-prevention assistance requires the original typed Baltimore City court-ordered eviction (photocopies not accepted), the client to be on the lease, photo ID, and receipts/promissory notes; the eviction assistance is available once in a lifetime. Dental services are limited to emergency care such as extractions (not routine dental care) and are provided by referral. Specific Responsive Services department hours and location are noted on the Center site (2nd floor for Responsive Services). | H37: Monday: 10 AM to 1 PM; Tuesday: 10 AM to 1 PM, 5:30 to 7 PM; Wednesday: 10 AM to 1 PM, 5:30 to 7 PM; Thursday: 10 AM to 1 PM; Friday: 10 AM to 1 PM; Saturday: Closed; Sunday: Closed | I37: Youth, Family, & General Support Services | J37: A long-established Baltimore center offering on-site emergency assistance and supportive outreach, including regular hot meals, an emergency food pantry/distribution program, identification and document help, clothing and baby-item distributions, case-management/referral services, job-readiness and culinary training, and limited emergency dental referrals. | K37: http://fcbmore.org/ | L37: Google reviewers commonly praise the Center as a community staple with caring staff and steady access to meals and essential supplies. Recurring concerns in recent reviews focus on rude or disrespectful behavior by security or frontline staff and occasional reports of delays or problems when seeking document assistance. The organization appears responsive to feedback (owners reply frequently), and public records/website corroboration indicate an active, established operation. | M37: 78.674499 | N37: 91.992693 | O37: accepted google identity: 14.2/15; review volume: 30.0/30; review consistency: 1.1/7; review freshness: 7.4/8; verified website: 14.2/15; confirmed irs record: 20.0/20; source corroboration: 5.0/5; Synthesis metadata: high (not part of numeric confidence) | P37: 8312026 | Q37: =IF(OR(ISBLANK(M37), ISBLANK(N37)), "", IF(N37 < Sheet3!$B$6, "Insufficient Reviews", IF(M37 >= Sheet3!$B$2, "Highly Reliable", IF(M37 >= Sheet3!$B$3, "Reliable", IF(M37 >= Sheet3!$B$4, "Mixed Reviews", "Low Reliability"))))) -> Reliable
A38: =A37+1 -> 37 | B38: 1900 Bayard St, Baltimore, MD 21230 | C38: 39.273679 | D38: -76.629389 | E38: (410) 834-5311 | F38: FLO - Friendly Loving Opportunities | ReBorn Store |NonProfit Organization in Baltimore | G38: Appears to serve people experiencing hardship, explicitly naming veterans, families in need, and people experiencing homelessness (per Google Maps owner description). Accepts donations and operates a retail store. Some reviewers report receiving assistance via referrals (e.g., from a medical office or Red Cross) for replacement furniture after disasters; this suggests referrals may be used in at least some cases, but referral requirements are not documented on an official intake page. | H38: Monday: 9 AM to 5 PM; Tuesday: Closed; Wednesday: 9 AM to 5 PM; Thursday: 9 AM to 5 PM; Friday: 9 AM to 5 PM; Saturday: 9 AM to 5 PM; Sunday: 9 AM to 5 PM | I38: Food & Essential Needs | J38: Organization operating a physical location in Baltimore that accepts donations and provides donated furniture, clothing, food, and household supplies to people experiencing hardship; also operates a vintage furniture store and offers pickup and delivery of donated items. | K38: http://flogiving.org/ | L38: Google reviewers most often praise respectful, welcoming staff, prompt pickup/donation handling, and helpfulness when providing furniture and related aid; multiple reviews describe free or low-cost furniture deliveries after referrals or disasters. Recurring concerns in the review text include at least one allegation of selective assistance or long waits for applicants and a few comments about higher retail prices for some used items. The newest reviews remain largely positive, describing good service and successful furniture assistance. | M38: 79.539502 | N38: 93.618867 | O38: accepted google identity: 14.2/15; review volume: 30.0/30; review consistency: 2.7/7; review freshness: 7.4/8; verified website: 14.2/15; confirmed irs record: 20.0/20; source corroboration: 5.0/5; Synthesis metadata: high (not part of numeric confidence) | P38: 8312026 | Q38: =IF(OR(ISBLANK(M38), ISBLANK(N38)), "", IF(N38 < Sheet3!$B$6, "Insufficient Reviews", IF(M38 >= Sheet3!$B$2, "Highly Reliable", IF(M38 >= Sheet3!$B$3, "Reliable", IF(M38 >= Sheet3!$B$4, "Mixed Reviews", "Low Reliability"))))) -> Reliable
A39: =A38+1 -> 38 | B39: 425 N Chester St, Baltimore, MD 21231 | C39: 39.296174 | D39: -76.587431 | E39: (410) 563-2749 | F39: Bea Gaddy Family Center Inc | G39: States it serves neighbors throughout the Greater Baltimore Metropolitan Area and Maryland and that its focus includes children and senior citizens. | H39: Monday: 9 AM to 5 PM; Tuesday: 9 AM to 5 PM; Wednesday: 9 AM to 5 PM; Thursday: 9 AM to 5 PM; Friday: 9 AM to 5 PM; Saturday: 9 AM to 5 PM; Sunday: 9 AM to 5 PM | I39: Food & Essential Needs | J39: A community-based organization that provides food and material assistance to neighbors in the Baltimore area and runs programs aimed at helping vulnerable populations, especially children and senior citizens. | K39: http://bea-gaddy.org/ | L39: Google Maps reviewers commonly praise the organization for providing food and being available to help community members, while a recurring concern in reviews is the quality of phone/customer service and occasional reports of being turned away without referrals. The most recent reviews in the fetched sample are mixed but include multiple positive ratings; reviewer text is limited in the newest entries. The organization’s website and a corroborating IRS BMF record further support the identity and ongoing operation of the listing. | M39: 74.466364 | N39: 85.631211 | O39: accepted google identity: 14.2/15; review volume: 26.4/30; review consistency: 0.9/7; review freshness: 4.9/8; verified website: 14.2/15; confirmed irs record: 20.0/20; source corroboration: 5.0/5; Synthesis metadata: high (not part of numeric confidence) | P39: 8312026 | Q39: =IF(OR(ISBLANK(M39), ISBLANK(N39)), "", IF(N39 < Sheet3!$B$6, "Insufficient Reviews", IF(M39 >= Sheet3!$B$2, "Highly Reliable", IF(M39 >= Sheet3!$B$3, "Reliable", IF(M39 >= Sheet3!$B$4, "Mixed Reviews", "Low Reliability"))))) -> Reliable
A40: =A39+1 -> 39 | B40: 424 S Pulaski St, Baltimore, MD 21223 | C40: 39.281773 | D40: -76.650528 | E40: (410) 429-0657 | F40: So What Else | G40: Donations: the site asks donors to contact the Baltimore location first to schedule drop-off and reserves the right to refuse items that are unclean, broken, or unsafe; some items (e.g., unopened diapers) have specific acceptance rules and large furniture requires advance email. Volunteer sign-up is handled through the organization’s volunteer hub. Community service hours require the student’s career center or professor to email the organization with program guidelines. Internships require an application including school contact, dates, hours, goals, and in‑person/remote split as requested by the site. | H40: Monday: Closed; Tuesday: 9 AM to 2 PM; Wednesday: 9 AM to 2 PM; Thursday: 9 AM to 2 PM; Friday: 9 AM to 2 PM; Saturday: 9 AM to 2 PM; Sunday: Closed | I40: Food & Essential Needs | J40: So What Else – Baltimore Resource Center operates a physical Baltimore location that coordinates Baltimore-specific food support activities and community engagement. The organization advertises accepting monetary and in-kind donations, runs volunteer opportunities and internship/community-service placements, and invites organizational partnerships in Baltimore. | K40: https://sowhatelse.org/food-rescue-bank/baltimore-food-giveaways/ | L40: There are no public user reviews available for this Google Maps listing, so direct user feedback is unavailable. Operational signals include a reachable, organization-published website page that describes Baltimore-specific donation, volunteer, internship, and food-support activities, and a Google Maps listing that provides an address, phone number, and published hours. Because public review text is absent, information here is based on the organization’s own published pages and archived snapshots; callers should confirm program details with the Baltimore Resource Center before relying on schedules or intake procedures. | M40: 16.5 | N40: 31.833333 | O40: accepted google identity: 14.2/15; review volume: 0.0/30; review consistency: 0.0/7; review freshness: 0.0/8; verified website: 14.2/15; confirmed irs record: 0.0/20; source corroboration: 3.3/5; Synthesis metadata: medium (not part of numeric confidence) | P40: 8312026 | Q40: =IF(OR(ISBLANK(M40), ISBLANK(N40)), "", IF(N40 < Sheet3!$B$6, "Insufficient Reviews", IF(M40 >= Sheet3!$B$2, "Highly Reliable", IF(M40 >= Sheet3!$B$3, "Reliable", IF(M40 >= Sheet3!$B$4, "Mixed Reviews", "Low Reliability"))))) -> Insufficient Reviews
A41: =A40+1 -> 40 | B41: 4711 Edmondson Ave, Baltimore, MD 21229 | C41: 39.292225 | D41: -76.699099 | E41: (410) 233-4357 | F41: 40 West Assistance & Referral Center | G41: Choice pantry access is limited to Baltimore City residents in ZIP codes 21207, 21229, 21215, 21216, and 21223; first-time visitors for the choice pantry are limited to residents of 21207 and 21229. TEFAP and Pantry On The Go distributions are not subject to the ZIP-code restriction. Food distributions are available on a monthly basis per household for the choice pantry and TEFAP (website states monthly access). | H41: Monday: 10 AM to 1 PM; Tuesday: Closed; Wednesday: 10 AM to 1 PM; Thursday: Closed; Friday: 10 AM to 1 PM; Saturday: Closed; Sunday: Closed | I41: Food & Essential Needs | J41: A neighborhood assistance and referral center that provides food distributions (choice pantry, federally funded TEFAP distributions, seasonal Pantry On The Go and holiday meal distributions) and helps neighbors with emergency needs such as utility payments, prescription assistance, temporary shelter, emergency transportation, clothing, and referrals to housing and employment services. | K41: http://www.40west.org/ | L41: Public Google Maps reviews are overwhelmingly positive: reviewers report receiving helpful assistance and food (several comments explicitly mention food distributions and getting the help they needed), and the newest reviews continue that positive trend. The organization’s own website provides detailed program descriptions (choice pantry, TEFAP, Pantry On The Go, utility/prescription help, transportation, shelter referrals) that align with reviewer reports. The listing is corroborated by a reachable official website and an IRS Business Master File match, which together strengthen the identity and operational signals. | M41: 80.812658 | N41: 93.157408 | O41: accepted google identity: 14.2/15; review volume: 30.0/30; review consistency: 6.0/7; review freshness: 3.7/8; verified website: 14.2/15; confirmed irs record: 20.0/20; source corroboration: 5.0/5; Synthesis metadata: high (not part of numeric confidence) | P41: 8312026 | Q41: =IF(OR(ISBLANK(M41), ISBLANK(N41)), "", IF(N41 < Sheet3!$B$6, "Insufficient Reviews", IF(M41 >= Sheet3!$B$2, "Highly Reliable", IF(M41 >= Sheet3!$B$3, "Reliable", IF(M41 >= Sheet3!$B$4, "Mixed Reviews", "Low Reliability"))))) -> Reliable
A42: =A41+1 -> 41 | B42: 2422 W Patapsco Ave, Baltimore, MD 21230 | C42: 39.252692 | D42: -76.650475 | E42: (410) 525-0969 | F42: Fishes & Loaves Pantry | G42: Photo I.D. with current address is requested but stated as not required. The pantry follows posted eligibility guidelines (website references proof-of-income or residency guidance) and notes that supplies are based on availability. Delivery is not offered; site is located near bus routes 71, 73, and 29. Google listing indicates a wheelchair-accessible parking lot and restroom but lists the entrance as not wheelchair accessible. | H42: Monday: 9:30 AM to 12 PM, 1 to 3 PM; Tuesday: 9:30 AM to 12 PM, 1 to 3 PM; Wednesday: 9:30 AM to 12 PM, 1 to 3 PM; Thursday: 9:30 AM to 12 PM, 1 to 3 PM; Friday: 9:30 AM to 12 PM, 1 to 3 PM; Saturday: Closed; Sunday: Closed | I42: Food & Essential Needs | J42: A neighborhood food pantry that distributes free groceries (both perishable and non-perishable), occasional frozen meat and fresh produce, and a limited selection of hygiene and household items; also provides some infant/toddler supplies and accepts donations and volunteers. | K42: https://www.flpbaltimore.org/ | L42: Google Maps review text shows many users praising the pantry’s organization, variety of food, and helpful volunteers, and several report gratitude that it keeps community members fed. Recurring concerns in reviews include limited portions for larger families, car-oriented operations that can make pedestrian access difficult, and occasional reports of unfriendly or strict volunteer interactions; a recent negative review emphasizes those accessibility and demeanor issues. The organization’s official website and recent IRS BMF filing corroborate the pantry’s identity and operational presence. | M42: 80.077344 | N42: 93.079088 | O42: accepted google identity: 14.2/15; review volume: 30.0/30; review consistency: 1.6/7; review freshness: 7.9/8; verified website: 14.2/15; confirmed irs record: 20.0/20; source corroboration: 5.0/5; Synthesis metadata: high (not part of numeric confidence) | P42: 8312026 | Q42: =IF(OR(ISBLANK(M42), ISBLANK(N42)), "", IF(N42 < Sheet3!$B$6, "Insufficient Reviews", IF(M42 >= Sheet3!$B$2, "Highly Reliable", IF(M42 >= Sheet3!$B$3, "Reliable", IF(M42 >= Sheet3!$B$4, "Mixed Reviews", "Low Reliability"))))) -> Reliable
A43: =A42+1 -> 42 | B43: 1118 Ward St, Baltimore, MD 21230 | C43: 39.282042 | D43: -76.632861 | E43: (410) 625-0775 | F43: Paul's Place, Inc | G43: Food distributed via partner network; use ‘Find Food’ tool | H43: Monday: 8 AM to 2 PM; Tuesday: 8 AM to 2 PM; Wednesday: 8 AM to 2 PM; Thursday: 8 AM to 2 PM; Friday: 8 AM to 2 PM; Saturday: Closed; Sunday: Closed | I43: Food & Essential Needs | J43: A physical community outreach center in Southwest Baltimore offering onsite programs and services to support individuals and families. Available services reported in provider information and reviewer tags include a regular lunch/feeding program, clothing and interview-attire assistance, help obtaining IDs or birth certificates, and housing-related case-management support. Services are delivered in person at the listed Ward Street location. | K43: http://www.paulsplaceoutreach.org/ | L43: Google reviewers consistently report helpful, friendly staff and frequent on-site food distribution; many reviewers also mention clothing help, ID/birth-certificate assistance, and housing or case-management support. Recent reviews in the fetched sample remain positive, and reviewers frequently note volunteer involvement and appreciation for the meals and community support. The organization’s website response was minimal when fetched (HTTP 202) but the Google Maps listing, recent reviews, and Wayback snapshots corroborate ongoing onsite activity. | M43: 78.308721 | N43: 73.376851 | O43: accepted google identity: 14.2/15; review volume: 30.0/30; review consistency: 5.5/7; review freshness: 6.1/8; verified website: 14.2/15; confirmed irs record: 0.0/20; source corroboration: 3.3/5; Synthesis metadata: high (not part of numeric confidence) | P43: 8312026 | Q43: =IF(OR(ISBLANK(M43), ISBLANK(N43)), "", IF(N43 < Sheet3!$B$6, "Insufficient Reviews", IF(M43 >= Sheet3!$B$2, "Highly Reliable", IF(M43 >= Sheet3!$B$3, "Reliable", IF(M43 >= Sheet3!$B$4, "Mixed Reviews", "Low Reliability"))))) -> Reliable
A44: =A43+1 -> 43 | B44: 2405 Linden Ave, Baltimore, MD 21217 | C44: 39.314184 | D44: -76.635553 | E44: (410) 669-2612 | F44: St. Francis Neighborhood Center | G44: Most programs are offered at no cost but youth programs require prior registration and serve residents who live, work, or attend school in the 21217 ZIP code. The center operates onsite services and lists dedicated senior hours (Tuesday, 9 AM–12 PM). The facility reports wheelchair-accessible entrance, parking, and restrooms. No additional eligibility or document requirements are specified in the available sources. | H44: Monday: 9 AM to 6 PM; Tuesday: 9 AM to 6 PM; Wednesday: 9 AM to 6 PM; Thursday: 9 AM to 6 PM; Friday: Closed; Saturday: Closed; Sunday: Closed | I44: Youth, Family, & General Support Services | J44: A neighborhood community center that provides free, in-person programs and supports for local residents, including youth after-school and summer programming, services for seniors, food distribution, and youth employment/internship opportunities. Services are delivered on-site at the Linden Avenue location. | K44: http://www.stfranciscenter.org/ | L44: Google reviewers consistently describe the center as a welcoming community hub with helpful staff, visible youth programming, and recurring food distribution events; many reviews praise the facility space and staff responsiveness. There are no recurring negative themes in the recent review sample and the newest reviews continue the positive trend. The organization’s website and an IRS registry match corroborate the listing’s identity and program descriptions, providing additional verification beyond public reviews. | M44: 87.204948 | N44: 94.990279 | O44: accepted google identity: 14.2/15; review volume: 30.0/30; review consistency: 3.7/7; review freshness: 7.8/8; verified website: 14.2/15; confirmed irs record: 20.0/20; source corroboration: 5.0/5; Synthesis metadata: high (not part of numeric confidence) | P44: 8312026 | Q44: =IF(OR(ISBLANK(M44), ISBLANK(N44)), "", IF(N44 < Sheet3!$B$6, "Insufficient Reviews", IF(M44 >= Sheet3!$B$2, "Highly Reliable", IF(M44 >= Sheet3!$B$3, "Reliable", IF(M44 >= Sheet3!$B$4, "Mixed Reviews", "Low Reliability"))))) -> Highly Reliable
A45: =A44+1 -> 44 | B45: 435 E 25th St, Baltimore, MD 21218 | C45: 39.317883 | D45: -76.610054 | E45: (410) 889-3001 | F45: Manna House Inc | G45: Website and listing identify the primary clientele as homeless and low-income residents of Baltimore. No explicit evidence found for required identification, referrals, intake documents, or fees. | H45: Monday: 8 AM to 3 PM; Tuesday: 8 AM to 3 PM; Wednesday: 8 AM to 3 PM; Thursday: 8 AM to 3 PM; Friday: 8 AM to 3 PM; Saturday: Closed; Sunday: Closed | I45: Food & Essential Needs | J45: Provides meal service focused on breakfast, operates a day/drop-in center where people can remain after meals, and offers case management, referrals, and food-distribution/pantry support aimed at people experiencing homelessness and low income in Baltimore. | K45: http://mannahouseinc.org/ | L45: Recent Google reviewers in the fetched sample consistently praise staff helpfulness, cleanliness, and the quality of food; reviewers also note positive experiences with donation handling. The sampled recent feedback is uniformly positive, but the listing’s broader historical rating is lower (4.1 overall from 82 public reviews), suggesting more variable experiences over time. The organization’s official website is reachable and corroborates the basic service offerings, though it also contains statements (e.g., daily breakfast year-round) that differ from the Google Maps hours. | M45: 73.589008 | N45: 65.043549 | O45: accepted google identity: 14.2/15; review volume: 22.8/30; review consistency: 7.0/7; review freshness: 3.4/8; verified website: 14.2/15; confirmed irs record: 0.0/20; source corroboration: 3.3/5; Synthesis metadata: medium (not part of numeric confidence) | P45: 8312026 | Q45: =IF(OR(ISBLANK(M45), ISBLANK(N45)), "", IF(N45 < Sheet3!$B$6, "Insufficient Reviews", IF(M45 >= Sheet3!$B$2, "Highly Reliable", IF(M45 >= Sheet3!$B$3, "Reliable", IF(M45 >= Sheet3!$B$4, "Mixed Reviews", "Low Reliability"))))) -> Reliable
A46: =A45+1 -> 45 | B46: 9201 Green Valley Rd, Union Bridge, MD 21791 | C46: 39.486871 | D46: -77.240458 | E46: (301) 898-5111 | F46: St. Peter the Apostle Roman Catholic Church | G46: The parish posts specific Mass and confession times and explicitly invites visitors to worship. Confession is listed with set times and also “or by appointment.” The site indicates at least one Mass is live-streamed (redirect to Facebook). No documentation of formal eligibility restrictions, intake paperwork, or referral requirements was found in the available sources. | H46: Monday: 9 AM to 5 PM; Tuesday: 9 AM to 5 PM; Wednesday: 9 AM to 5 PM; Thursday: 9 AM to 5 PM; Friday: 9 AM to 5 PM; Saturday: Closed; Sunday: Closed | I46: Youth, Family, & General Support Services | J46: A local Roman Catholic parish offering regular worship (Mass), confession and other sacramental services, parish ministries and community outreach, plus children’s faith-formation and youth programs. The parish also provides at least one live-streamed Mass and publishes schedules for services and confessions. | K46: http://www.stpeter-libertytown.org/ | L46: Public Google Maps reviewers consistently describe the parish as welcoming and friendly, noting active ministries and opportunities for prayer (one reviewer specifically mentions a 24-hour adoration chapel). Occasional minor complaints appear in the sample—comments about noisy children during services and an isolated unrelated/unclear complaint—but most recent reviews remain positive. Overall, reviewer feedback is plentiful and consistently affirms a positive parish experience. | M46: 83.360885 | N46: 74.902767 | O46: accepted google identity: 14.2/15; review volume: 30.0/30; review consistency: 5.4/7; review freshness: 7.7/8; verified website: 14.2/15; confirmed irs record: 0.0/20; source corroboration: 3.3/5; Synthesis metadata: high (not part of numeric confidence) | P46: 8312026 | Q46: =IF(OR(ISBLANK(M46), ISBLANK(N46)), "", IF(N46 < Sheet3!$B$6, "Insufficient Reviews", IF(M46 >= Sheet3!$B$2, "Highly Reliable", IF(M46 >= Sheet3!$B$3, "Reliable", IF(M46 >= Sheet3!$B$4, "Mixed Reviews", "Low Reliability"))))) -> Highly Reliable
A47: =A46+1 -> 46 | B47: 1214 N Wolfe St, Baltimore, MD 21213 | C47: 39.305076 | D47: -76.591542 | E47: (443) 478-3015 | F47: Charm City Care Connection | G47: Drop‑in hours and specific programs have published schedules; the site lists drop‑in hours as weekdays and a women‑only evening. Website lists outreach times and case‑management availability and asks callers to verify service availability by phone. The organization states a primary focus on serving people who use drugs. (See official website and Google listing for published hours and program notes.) | H47: Monday: 9 AM to 4 PM; Tuesday: 9 AM to 4 PM; Wednesday: 9 AM to 4 PM; Thursday: 9 AM to 4 PM; Friday: Closed; Saturday: Closed; Sunday: Closed | I47: Physical & General Health Care | J47: A staffed drop-in center in East Baltimore that provides low‑barrier health and harm‑reduction supports including safer drug‑use supplies, wound care and infectious‑disease testing, access to medications for opioid use disorder via a mobile buprenorphine program, basic hygiene services (showers, laundry, clothing), peer recovery and case‑management support, and outreach services in the neighborhood. | K47: https://www.charmcitycareconnection.org/ | L47: Google reviewers consistently report helpful, respectful staff and describe the location as a welcoming, nonjudgmental place that provides practical supports such as showers, clothing, and assistance for people experiencing homelessness and substance‑use concerns. A small number of reviews note minor delays or mixed experiences, but negative comments are uncommon in the sampled reviews. The most recent reviews remain strongly positive, and the organization’s website and Google listing consistently document the same core services and published hours. | M47: 88.157997 | N47: 75.614967 | O47: accepted google identity: 14.2/15; review volume: 30.0/30; review consistency: 6.1/7; review freshness: 7.7/8; verified website: 14.2/15; confirmed irs record: 0.0/20; source corroboration: 3.3/5; Synthesis metadata: high (not part of numeric confidence) | P47: 8312026 | Q47: =IF(OR(ISBLANK(M47), ISBLANK(N47)), "", IF(N47 < Sheet3!$B$6, "Insufficient Reviews", IF(M47 >= Sheet3!$B$2, "Highly Reliable", IF(M47 >= Sheet3!$B$3, "Reliable", IF(M47 >= Sheet3!$B$4, "Mixed Reviews", "Low Reliability"))))) -> Highly Reliable
A48: =A47+1 -> 47 | B48: 1111 N Charles St, Baltimore, MD 21201 | C48: 39.302708 | D48: -76.615546 | E48: (410) 837-2050 | F48: Chase Brexton Health Care - Mt. Vernon Center | G48: Accepts Medicaid, Medicare, and a wide range of commercial insurance plans and offers a sliding fee scale for uninsured or low-income patients. Social Work & Outreach provides assistance with insurance enrollment and referrals. The site lists dedicated appointment lines/teams for services at the Mt. Vernon center (including sexual health clinic appointments) and a Telehealth support line; some services are appointment-based. | H48: Monday: 8 AM to 7 PM; Tuesday: 8 AM to 7 PM; Wednesday: 8 AM to 7 PM; Thursday: 8 AM to 7 PM; Friday: 8 AM to 5 PM; Saturday: Closed; Sunday: Closed | I48: Physical & General Health Care | J48: A multi-service community health center at the Mt. Vernon location providing on-site primary medical care plus behavioral health, dental, pharmacy, sexual health/HIV services, laboratory services, case management, and patient-support programs (insurance help, referrals, and social services). | K48: http://www.chasebrexton.org/?utm_source=GMBSocialClimb&utm_medium=ChaseBrextonHealthServices | L48: Google reviewers repeatedly praise friendly, professional staff, an efficient on-site pharmacy, accessible and clean facilities, and care that meets diverse patient needs. Recurring negative notes focus on occasional long wait times. The most recent reviews continue to be positive, indicating that recent patient feedback aligns with earlier praise. | M48: 81.339276 | N48: 72.84847 | O48: accepted google identity: 14.2/15; review volume: 30.0/30; review consistency: 3.0/7; review freshness: 8.0/8; verified website: 14.2/15; confirmed irs record: 0.0/20; source corroboration: 3.3/5; Synthesis metadata: high (not part of numeric confidence) | P48: 8312026 | Q48: =IF(OR(ISBLANK(M48), ISBLANK(N48)), "", IF(N48 < Sheet3!$B$6, "Insufficient Reviews", IF(M48 >= Sheet3!$B$2, "Highly Reliable", IF(M48 >= Sheet3!$B$3, "Reliable", IF(M48 >= Sheet3!$B$4, "Mixed Reviews", "Low Reliability"))))) -> Reliable
... A50: =A49+1 -> 49 | B50: 3120 Erdman Ave, Baltimore, MD 21213 | C50: 39.321171 | D50: -76.572709 | E50: (410) 558-4800 | F50: Baltimore Medical System – Belair-Edison | G50: Appointments are recommended and the Google listing indicates appointments may be required; sliding-fee discounts and reduced rates are available based on household income. Health Benefit Advisors assist with insurance enrollment (staff availability noted Monday–Friday, with Saturday by appointment on some pages). Pharmacies accept most prescription plans and offer free prescription delivery to patients in certain ZIP codes (delivery eligibility must be checked). Language interpretation is available. | H50: Monday: 8 AM to 5 PM; Tuesday: 8 AM to 5 PM; Wednesday: 8 AM to 5 PM; Thursday: 8 AM to 5 PM; Friday: 8 AM to 5 PM; Saturday: Closed; Sunday: Closed | I50: Physical & General Health Care | J50: A community health center providing primary and family medical care for patients of all ages, on-site pharmacies (including a prescription delivery program), behavioral-health services, insurance enrollment and financial-assistance navigation, and patient support services such as language interpretation. | K50: https://www.bmsi.org/ | L50: Google reviewers report a mix of experiences: many praise caring front-line staff, specific clinicians and pharmacy/administrative help, and a clean, welcoming clinic environment; recurring negative themes include long waits, communication problems around prescription refills and referrals, and occasional reports of disrespectful or unresponsive providers/staff. The listing owner has responded publicly to critical feedback in several cases. The newest reviews in the fetched sample are more positive than some earlier complaints, suggesting recent visits reported improved experiences by some patients. | M50: 61.769704 | N50: 68.623057 | O50: accepted google identity: 13.5/15; review volume: 30.0/30; review consistency: 0.7/7; review freshness: 7.6/8; verified website: 13.5/15; confirmed irs record: 0.0/20; source corroboration: 3.3/5; Synthesis metadata: high (not part of numeric confidence) | P50: 8312026 | Q50: =IF(OR(ISBLANK(M50), ISBLANK(N50)), "", IF(N50 < Sheet3!$B$6, "Insufficient Reviews", IF(M50 >= Sheet3!$B$2, "Highly Reliable", IF(M50 >= Sheet3!$B$3, "Reliable", IF(M50 >= Sheet3!$B$4, "Mixed Reviews", "Low Reliability"))))) -> Mixed Reviews
A51: =A50+1 -> 50 | B51: 1501 Division St, Baltimore, MD 21217 | C51: 39.303278 | D51: -76.631647 | E51: (410) 383-8300 | F51: Total Health Care | H51: Monday: 8:30 AM to 7 PM; Tuesday: 8:30 AM to 7 PM; Wednesday: 8:30 AM to 7 PM; Thursday: 8:30 AM to 7 PM; Friday: 8:30 AM to 6 PM; Saturday: Closed; Sunday: Closed | I51: Physical & General Health Care | J51: A multi-service medical clinic offering on-site primary care (internal medicine), dental services, obstetrics/gynecology, infectious disease care, pediatric care, mental-health services, and a pharmacy. | K51: http://totalhealthcare.org/ | L51: Google Maps reviewers frequently praise friendly, long‑term relationships with staff and positive experiences in adult medicine, with multiple recent posts thanking specific clinicians and teams. Recurring concerns in reviews include poor communication (patient-portal responsiveness), problems coordinating referrals and billing, and a few reports of painful dental procedures or unsatisfactory dental care. Owner responses are present on many reviews; the newest reviews are a mix of praise and complaint, so feedback remains mixed but with continued positive reports about staff and some persistent service issues. | M51: 71.149395 | N51: 92.524701 | O51: accepted google identity: 14.2/15; review volume: 30.0/30; review consistency: 1.4/7; review freshness: 7.6/8; verified website: 14.2/15; confirmed irs record: 20.0/20; source corroboration: 5.0/5; Synthesis metadata: high (not part of numeric confidence) | P51: 8312026 | Q51: =IF(OR(ISBLANK(M51), ISBLANK(N51)), "", IF(N51 < Sheet3!$B$6, "Insufficient Reviews", IF(M51 >= Sheet3!$B$2, "Highly Reliable", IF(M51 >= Sheet3!$B$3, "Reliable", IF(M51 >= Sheet3!$B$4, "Mixed Reviews", "Low Reliability"))))) -> Reliable
A52: =A51+1 -> 51 | B52: 430 S Broadway, Baltimore, MD 21231 | C52: 39.285784 | D52: -76.593833 | E52: (667) 600-2900 | F52: Esperanza Center | G52: Services are described on the site as focused on immigrants; prospective clients are asked to contact the center for inquiries (website contact form indicates all fields required). No documented fees, required documents, or referral process were found in the provided sources. | H52: Monday: 9 AM to 4:30 PM; Tuesday: 9 AM to 4:30 PM; Wednesday: 9 AM to 4:30 PM; Thursday: 9 AM to 4:30 PM; Friday: 9 AM to 4:35 PM; Saturday: Open 24 hours; Sunday: Closed | I52: Physical & General Health Care | J52: A community resource center serving immigrants that provides on-site health care (medical and dental, including primary and preventive care), immigration legal assistance and counseling, housing and social services, employment and education supports, and victim case management/advocacy. | K52: http://www.catholiccharities-md.org/immigrants/?referrer=https://www.google.co.in/ | L52: Google reviewers repeatedly praise staff helpfulness and attentive service, and several reviewers note Spanish-language support and positive outcomes from counseling they received. A small but recurring negative theme concerns front-desk interactions or individual staff members. The most recent reviews continue to emphasize positive experiences, and the organization’s website corroborates a broad set of immigrant-focused health, legal, and social programs. | M52: 80.301544 | N52: 69.574956 | O52: accepted google identity: 13.5/15; review volume: 30.0/30; review consistency: 1.4/7; review freshness: 7.8/8; verified website: 13.5/15; confirmed irs record: 0.0/20; source corroboration: 3.3/5; Synthesis metadata: high (not part of numeric confidence) | P52: 8312026 | Q52: =IF(OR(ISBLANK(M52), ISBLANK(N52)), "", IF(N52 < Sheet3!$B$6, "Insufficient Reviews", IF(M52 >= Sheet3!$B$2, "Highly Reliable", IF(M52 >= Sheet3!$B$3, "Reliable", IF(M52 >= Sheet3!$B$4, "Mixed Reviews", "Low Reliability"))))) -> Reliable
A53: =A52+1 -> 52 | B53: 900 S Caton Ave, Baltimore, MD 21229 | C53: 39.271701 | D53: -76.673529 | E53: (667) 234-6000 | F53: Ascension Saint Agnes Hospital | G53: M-T 8AM-7PM, F 8AM-5PM | H53: Monday: Open 24 hours; Tuesday: Open 24 hours; Wednesday: Open 24 hours; Thursday: Open 24 hours; Friday: Open 24 hours; Saturday: Open 24 hours; Sunday: Open 24 hours | I53: Physical & General Health Care | J53: A full-service acute-care hospital and emergency department providing inpatient and outpatient clinical care across multiple specialties, including surgical and specialty services, maternity/OB-GYN, cancer care, cardiac care, imaging/laboratory diagnostics, and rehabilitation. The site also hosts graduate medical education (residency) programs. | K53: https://healthcare.ascension.org/locations/maryland/mdbal/baltimore-ascension-saint-agnes-hospital?utm_campaign=gmb&utm_medium=organic-search&utm_content=location-listing&utm_source=local | L53: Google reviews show many recent accounts praising attentive clinical teams, positive surgical outcomes, and good maternity experiences; several reviewers specifically note helpful staff and satisfactory post-op care. Recurring negative themes in reviews include long emergency-department wait times, concerns about cleanliness, and perceived understaffing on some inpatient units. The most recent reviews in the fetched sample trend positively, though critical reports about the ED and staffing continue to appear intermittently. | M53: 71.925881 | N53: 71.502292 | O53: accepted google identity: 14.2/15; review volume: 30.0/30; review consistency: 1.7/7; review freshness: 8.0/8; verified website: 14.2/15; confirmed irs record: 0.0/20; source corroboration: 3.3/5; Synthesis metadata: high (not part of numeric confidence) | P53: 8312026 | Q53: =IF(OR(ISBLANK(M53), ISBLANK(N53)), "", IF(N53 < Sheet3!$B$6, "Insufficient Reviews", IF(M53 >= Sheet3!$B$2, "Highly Reliable", IF(M53 >= Sheet3!$B$3, "Reliable", IF(M53 >= Sheet3!$B$4, "Mixed Reviews", "Low Reliability"))))) -> Reliable
A54: =A53+1 -> 53 | B54: 1800 Orleans St, Baltimore, MD 21287 | C54: 39.296738 | D54: -76.592736 | E54: (410) 955-5000 | F54: The Johns Hopkins Hospital | G54: City residents; program eligibility varies | H54: Monday: Open 24 hours; Tuesday: Open 24 hours; Wednesday: Open 24 hours; Thursday: Open 24 hours; Friday: Open 24 hours; Saturday: Open 24 hours; Sunday: Open 24 hours | I54: Physical & General Health Care | J54: An academic medical center and hospital that provides inpatient and outpatient medical care, emergency (ER) services, and participates in clinical care, research, and education. | K54: https://www.hopkinsmedicine.org/the_johns_hopkins_hospital/?utm_source=Google&utm_medium=Organic&utm_campaign=Yext&utm_content=FAD&utm_keyword=JHH | L54: Google reviewers frequently praise individual clinicians and certain teams for being thorough, compassionate, and technically skilled. Recurring concerns in reviews include long emergency-room wait times and reports of poor interactions or problems with aspects of inpatient care; some reviewers describe serious negative experiences. The most recent reviews continue to show a mix of strong praise and strong complaints, and the organization commonly posts responses to reviewer feedback. | M54: 63.778375 | N54: 70.083588 | O54: accepted google identity: 14.2/15; review volume: 30.0/30; review consistency: 0.3/7; review freshness: 8.0/8; verified website: 14.2/15; confirmed irs record: 0.0/20; source corroboration: 3.3/5; Synthesis metadata: high (not part of numeric confidence) | P54: 8312026 | Q54: =IF(OR(ISBLANK(M54), ISBLANK(N54)), "", IF(N54 < Sheet3!$B$6, "Insufficient Reviews", IF(M54 >= Sheet3!$B$2, "Highly Reliable", IF(M54 >= Sheet3!$B$3, "Reliable", IF(M54 >= Sheet3!$B$4, "Mixed Reviews", "Low Reliability"))))) -> Mixed Reviews
A55: =A54+1 -> 54 | B55: 3001 S Hanover St, Baltimore, MD 21225 | C55: 39.251958 | D55: -76.614307 | E55: (410) 350-3200 | F55: MedStar Harbor Hospital | G55: Emergency department is open 24/7. The Food Rx program serves qualified patients with diabetes related to food insecurity. The MedStar eVisit telehealth option is available 24/7 on demand; patients create an account and may verify insurance at time of service (a self-pay price is published for uninsured users). | H55: Monday: Open 24 hours; Tuesday: Open 24 hours; Wednesday: Open 24 hours; Thursday: Open 24 hours; Friday: Open 24 hours; Saturday: Open 24 hours; Sunday: Open 24 hours | I55: Physical & General Health Care | J55: MedStar Harbor Hospital is a full-service community hospital offering emergency care plus inpatient and outpatient services across multiple specialties, including internal medicine, surgery, obstetrics, orthopedics, behavioral health, and diabetes care. The hospital also runs community-focused programs such as a mobile health center and a medically tailored Food Rx program. | K55: https://www.medstarhealth.org/locations/medstar-harbor-hospital?utm_campaign=mhs_citations&utm_medium=listing&utm_source=citation_management&utm_term=hospital | L55: Google reviewers commonly praise caring, professional staff and specific clinicians across specialties, reporting good bedside manner and coordinated care. Recurring concerns in reviews include long emergency-department wait times and occasional facility/amenity complaints (for example, room water pressure and food service). The newest reviews in the fetched sample remain mostly positive, and the listing owner regularly posts responses to reviewers. | M55: 83.303584 | N55: 94.919721 | O55: accepted google identity: 14.2/15; review volume: 30.0/30; review consistency: 3.4/7; review freshness: 8.0/8; verified website: 14.2/15; confirmed irs record: 20.0/20; source corroboration: 5.0/5; Synthesis metadata: high (not part of numeric confidence) | P55: 8312026 | Q55: =IF(OR(ISBLANK(M55), ISBLANK(N55)), "", IF(N55 < Sheet3!$B$6, "Insufficient Reviews", IF(M55 >= Sheet3!$B$2, "Highly Reliable", IF(M55 >= Sheet3!$B$3, "Reliable", IF(M55 >= Sheet3!$B$4, "Mixed Reviews", "Low Reliability"))))) -> Highly Reliable
A56: =A55+1 -> 55 | B56: 140 W West St, Baltimore, MD 21230 | C56: 39.276181 | D56: -76.618451 | E56: (410) 752-4454 | F56: The Baltimore Station | G56: Agency referral typically required | H56: Monday: Open 24 hours; Tuesday: Open 24 hours; Wednesday: Open 24 hours; Thursday: Open 24 hours; Friday: Open 24 hours; Saturday: Open 24 hours; Sunday: Open 24 hours | I56: Veteran Services | J56: A veteran-focused organization that operates therapeutic residential treatment and transitional housing programs to support veterans recovering from addiction, trauma, and homelessness; offers supportive services and life-skill classes and maintains on-site food distribution/meal support. | K56: https://baltimorestation.org/ | L56: Google Maps reviews fetched for the listing are consistently positive: reviewers repeatedly praise caring, welcoming staff and credit the program with helping veterans regain stability and recovery. The sampled recent reviews continue this positive trend, and there are few reported negative experiences in the fetched sample. The organization’s official website corroborates program-level claims (therapeutic residential treatment, transitional housing, classes) and the Maps listing shows active hours and contact details, providing consistent corroboration between platforms. | M56: 85.773789 | N56: 72.71889 | O56: accepted google identity: 14.2/15; review volume: 26.4/30; review consistency: 7.0/7; review freshness: 7.5/8; verified website: 14.2/15; confirmed irs record: 0.0/20; source corroboration: 3.3/5; Synthesis metadata: high (not part of numeric confidence) | P56: 8312026 | Q56: =IF(OR(ISBLANK(M56), ISBLANK(N56)), "", IF(N56 < Sheet3!$B$6, "Insufficient Reviews", IF(M56 >= Sheet3!$B$2, "Highly Reliable", IF(M56 >= Sheet3!$B$3, "Reliable", IF(M56 >= Sheet3!$B$4, "Mixed Reviews", "Low Reliability"))))) -> Highly Reliable
A57: =A56+1 -> 56 | B57: 2104 Maryland Ave, Baltimore, MD 21218 | C57: 39.313472 | D57: -76.618263 | E57: (410) 752-6850 | F57: REACH Health Services | H57: Monday: 5:30 AM to 12:30 PM; Tuesday: 5:30 AM to 12:30 PM; Wednesday: 5:30 AM to 12:30 PM; Thursday: 5:30 AM to 12:30 PM; Friday: 5:30 AM to 12:30 PM; Saturday: 6 to 8 AM; Sunday: Closed | I57: Behavioral Health, Substance Use, & Crisis | J57: Provides outpatient substance use disorder treatment and recovery services, including medication-assisted treatment and counseling delivered with a patient-centered, trauma‑informed approach. | K57: http://www.ibrinc.org/ | L57: Reviewers commonly praise specific counselors and describe the program as supportive, organized, and life-changing, with multiple recent comments highlighting staff who went above and beyond. At least one detailed negative account alleges a serious safety incident and problematic program handling, showing that some users have had adverse experiences. The most recent reviews remain positive, so recent feedback appears to lean favorable despite isolated serious complaints. | M57: 76.445589 | N57: 67.156221 | O57: accepted google identity: 13.5/15; review volume: 27.9/30; review consistency: 2.6/7; review freshness: 6.3/8; verified website: 13.5/15; confirmed irs record: 0.0/20; source corroboration: 3.3/5; Synthesis metadata: high (not part of numeric confidence) | P57: 8312026 | Q57: =IF(OR(ISBLANK(M57), ISBLANK(N57)), "", IF(N57 < Sheet3!$B$6, "Insufficient Reviews", IF(M57 >= Sheet3!$B$2, "Highly Reliable", IF(M57 >= Sheet3!$B$3, "Reliable", IF(M57 >= Sheet3!$B$4, "Mixed Reviews", "Low Reliability"))))) -> Reliable
A58: =A57+1 -> 57 | B58: 1212 N Wolfe St, Baltimore, MD 21213 | C58: 39.30497 | D58: -76.5921 | E58: (410) 759-8162 | F58: Dee's Place Wellness & Recovery Center | G58: The Google Maps listing states that all program services are provided free of charge and that the center was founded by and for people in recovery. No other eligibility, intake, referral, or documentation requirements are stated in the available evidence. | H58: Monday: Open 24 hours; Tuesday: Open 24 hours; Wednesday: Open 24 hours; Thursday: Open 24 hours; Friday: Open 24 hours; Saturday: Open 24 hours; Sunday: Open 24 hours | I58: Behavioral Health, Substance Use, & Crisis | J58: A community wellness and recovery center that provides peer-led recovery support services and wellness programming; the listing states all program services are free of charge. | K58: https://www.hebcac.org/deesplace | L58: Google Maps reviewers consistently describe the center as welcoming, supportive, and helpful to people in recovery, with multiple reviewers noting a positive atmosphere and reliable assistance. There are few criticisms in the fetched review sample and the most recent reviews continue to reflect positive experiences. Online corroboration is limited because the listed website returns an expired/404 page, reducing independent website-based verification. | M58: 83.147437 | N58: 71.808767 | O58: accepted google identity: 13.3/15; review volume: 27.7/30; review consistency: 6.2/7; review freshness: 8.0/8; verified website: 13.3/15; confirmed irs record: 0.0/20; source corroboration: 3.3/5; Synthesis metadata: high (not part of numeric confidence) | P58: 8312026 | Q58: =IF(OR(ISBLANK(M58), ISBLANK(N58)), "", IF(N58 < Sheet3!$B$6, "Insufficient Reviews", IF(M58 >= Sheet3!$B$2, "Highly Reliable", IF(M58 >= Sheet3!$B$3, "Reliable", IF(M58 >= Sheet3!$B$4, "Mixed Reviews", "Low Reliability"))))) -> Highly Reliable
A59: =A58+1 -> 58 | B59: 323 E 25th St, Baltimore, MD 21218 | C59: 39.317828 | D59: -76.611978 | E59: (410) 235-8877 | F59: At Jacobs Well Inc | G59: Office hours operate Monday–Friday, 9AM–4PM, with Saturday and Sunday closed; other times by appointment. Permanent Supportive Housing placements are by referral through The Mayor’s Office of Homeless Services. The program targets low-income men and women with mental health needs; prospective clients should contact the organization for intake details and eligibility screening. | H59: Monday – Friday: 9AM – 4PM Saturday: Closed Sunday: Closed other times by appointment | I59: Housing & Shelter | J59: A Baltimore-based organization that provides transitional and permanent supportive housing and related wrap-around services for people experiencing homelessness who have mental health needs. | K59: https://atjacobswell.org/ | L59: Google Maps review text for this listing is effectively unavailable or too thin to summarize user experiences: the fetched review sample contains no substantive comment, so reviewer themes cannot be reliably identified. The organization’s official website is reachable and provides detailed program descriptions (transitional and permanent housing, supportive services). An IRS/BMF registry match indicates an active filing in 2025, which corroborates the organization’s identity and ongoing operations. | M59: 70.397014 | N59: 73.571721 | O59: accepted google identity: 14.2/15; review volume: 10.1/30; review consistency: 7.0/7; review freshness: 3.0/8; verified website: 14.2/15; confirmed irs record: 20.0/20; source corroboration: 5.0/5; Synthesis metadata: high (not part of numeric confidence) | P59: 8312026 | Q59: =IF(OR(ISBLANK(M59), ISBLANK(N59)), "", IF(N59 < Sheet3!$B$6, "Insufficient Reviews", IF(M59 >= Sheet3!$B$2, "Highly Reliable", IF(M59 >= Sheet3!$B$3, "Reliable", IF(M59 >= Sheet3!$B$4, "Mixed Reviews", "Low Reliability"))))) -> Reliable
A60: =A59+1 -> 59 | B60: 112 E 25th St #1, Baltimore, MD 21218 | C60: 39.318182 | D60: -76.614638 | E60: (410) 566-0094 | F60: Pleasant Housing Inc. | G60: Program materials state eligibility is aimed at individuals stepping forward from substance abuse and those seeking help with homelessness, mental health, former incarceration, or HIV/AIDS-related concerns. No additional intake, referral, or documentation requirements are stated in the available sources. | H60: Monday: Closed; Tuesday: 10 AM to 5 PM; Wednesday: 10 AM to 5 PM; Thursday: 10 AM to 5 PM; Friday: 10 AM to 5 PM; Saturday: Closed; Sunday: Closed | I60: Housing & Shelter | J60: Pleasant Housing operates a supportive housing program that provides a structured living environment plus wraparound supports such as educational assistance, financial-management training, personal life-management help, and career/goal planning for people transitioning from homelessness, substance use, incarceration, or coping with mental health and HIV/AIDS-related challenges. | K60: https://www.pleasanthousing.com/ | L60: Reviewer comments that are available praise at least one staff member for being helpful, but otherwise describe serious concerns with cleanliness (including bed bugs and roaches), abrupt or poorly handled discharges, and unprofessional staff interactions that negatively affected residents. These themes recur in the recent reviewer accounts and the most recent feedback follows a similar pattern. Overall reviewer feedback is limited, so these comments may not represent the full range of client experiences. | M60: 48.388288 | N60: 52.167856 | O60: accepted google identity: 14.2/15; review volume: 11.3/30; review consistency: 5.2/7; review freshness: 3.8/8; verified website: 14.2/15; confirmed irs record: 0.0/20; source corroboration: 3.3/5; Synthesis metadata: medium (not part of numeric confidence) | P60: 8312026 | Q60: =IF(OR(ISBLANK(M60), ISBLANK(N60)), "", IF(N60 < Sheet3!$B$6, "Insufficient Reviews", IF(M60 >= Sheet3!$B$2, "Highly Reliable", IF(M60 >= Sheet3!$B$3, "Reliable", IF(M60 >= Sheet3!$B$4, "Mixed Reviews", "Low Reliability"))))) -> Low Reliability
A61: =A60+1 -> 60 | B61: 119 E 25th St, Baltimore, MD 21218 | C61: 39.317732 | D61: -76.614409 | E61: (410) 235-5782 | F61: Women’s Housing Coalition | G61: Website states adults served are formerly homeless, low-income or very-low-income, and have a federally-defined disability; the organization serves families and individuals with services tailored in collaboration with residents. (No website-evidenced details about required documents, referral sources, or intake steps were provided.) | H61: Monday: 9 AM to 5 PM; Tuesday: 9 AM to 5 PM; Wednesday: 9 AM to 5 PM; Thursday: 9 AM to 5 PM; Friday: 9 AM to 5 PM; Saturday: Closed; Sunday: Closed | I61: Housing & Shelter | J61: Provides permanent, affordable housing combined with supportive services for people who have experienced homelessness; services described include intensive one-to-one case management, resident advocacy, life-skills training, and rent/utility assistance tailored to individual or family needs. | K61: http://womenshousing.org/ | L61: Review text was unavailable or too thin to summarize reviewer experiences. The organization’s official website and a recent IRS filing corroborate its identity and activity, and the Google Maps listing provides published hours and accessibility details. These non-review signals consistently indicate an operational service provider at the listed Baltimore address. | M61: 61.2 | N61: 65.639003 | O61: accepted google identity: 14.2/15; review volume: 12.1/30; review consistency: 0.0/7; review freshness: 0.0/8; verified website: 14.2/15; confirmed irs record: 20.0/20; source corroboration: 5.0/5; Synthesis metadata: high (not part of numeric confidence) | P61: 8312026 | Q61: =IF(OR(ISBLANK(M61), ISBLANK(N61)), "", IF(N61 < Sheet3!$B$6, "Insufficient Reviews", IF(M61 >= Sheet3!$B$2, "Highly Reliable", IF(M61 >= Sheet3!$B$3, "Reliable", IF(M61 >= Sheet3!$B$4, "Mixed Reviews", "Low Reliability"))))) -> Mixed Reviews
A62: =A61+1 -> 61 | B62: 31 Hopkins Pl, Baltimore, MD 21201 | C62: 39.288128 | D62: -76.616699 | E62: (800) 827-1000 | F62: VA Baltimore Regional Office | G62: In-person services are by appointment only; visitors are encouraged to schedule virtual or in-person appointments via the VERA portal. Bring a current, unexpired photo ID. Depending on the visit, you may need to bring discharge/separation papers (DD214), relevant medical records, your Social Security number, direct deposit information, and information about dependents (dates of birth and Social Security numbers). The office can advise what documents are needed and may request documents on your behalf. | H62: Monday: 8:30 AM to 4 PM; Tuesday: 8:30 AM to 4 PM; Wednesday: 8:30 AM to 4 PM; Thursday: 8:30 AM to 4 PM; Friday: 8:30 AM to 4 PM; Saturday: Closed; Sunday: Closed | I62: Veteran Services | J62: A regional VA benefits office that helps veterans, service members, and their families apply for and manage VA benefits and services such as disability compensation, education benefits, life insurance, pensions, home loan eligibility/COE, and employment/readiness support; benefit counselors assist with eligibility, paperwork, and checking claim status. | K62: https://www.va.gov/baltimore-va-regional-benefit-office/ | L62: Public Google Maps reviews consistently report problems contacting the office, delayed or unhelpful responses, and several instances of customers saying cases or services were negatively affected by poor responsiveness; reviewers also recount rude interactions in some visits. A minority of reviewers single out specific staff for prompt, helpful assistance. Newer reviews continue to describe access and responsiveness problems, so recent feedback aligns with earlier negative reports. | M62: 55.126203 | N62: 69.632732 | O62: accepted google identity: 14.2/15; review volume: 28.8/30; review consistency: 1.2/7; review freshness: 7.8/8; verified website: 14.2/15; confirmed irs record: 0.0/20; source corroboration: 3.3/5; Synthesis metadata: high (not part of numeric confidence) | P62: 8312026 | Q62: =IF(OR(ISBLANK(M62), ISBLANK(N62)), "", IF(N62 < Sheet3!$B$6, "Insufficient Reviews", IF(M62 >= Sheet3!$B$2, "Highly Reliable", IF(M62 >= Sheet3!$B$3, "Reliable", IF(M62 >= Sheet3!$B$4, "Mixed Reviews", "Low Reliability"))))) -> Low Reliability
A63: =A62+1 -> 62 | B63: 10 N Greene St, Baltimore, MD 21201 | C63: 39.2899 | D63: -76.624477 | E63: (410) 605-7000 | F63: Baltimore VA Medical Center - VA Maryland Health Care System | G63: Serves patients of the VA Maryland Health Care System (Veterans). | H63: Monday: Open 24 hours; Tuesday: Open 24 hours; Wednesday: Open 24 hours; Thursday: Open 24 hours; Friday: Open 24 hours; Saturday: Open 24 hours; Sunday: Open 24 hours | I63: Physical & General Health Care | J63: A Veterans medical center providing acute medical and surgical care with inpatient and outpatient services, primary care, and serving as a neurosurgery referral center for the regional VA network. | L63: Google Maps reviewers commonly praise clinical staff across primary care and emergency settings for being attentive, competent, and compassionate. Recurring negative themes mention front-desk or reception rudeness and occasional long waits or difficulty getting timely attention. The most recent reviews trend positive, with multiple recent firsthand accounts describing good experiences in primary care and emergency care. | M63: 66.394856 | N63: 54.848379 | O63: accepted google identity: 14.2/15; review volume: 30.0/30; review consistency: 1.2/7; review freshness: 7.7/8; verified website: 0.0/15; confirmed irs record: 0.0/20; source corroboration: 1.7/5; Synthesis metadata: high (not part of numeric confidence) | P63: 8312026 | Q63: =IF(OR(ISBLANK(M63), ISBLANK(N63)), "", IF(N63 < Sheet3!$B$6, "Insufficient Reviews", IF(M63 >= Sheet3!$B$2, "Highly Reliable", IF(M63 >= Sheet3!$B$3, "Reliable", IF(M63 >= Sheet3!$B$4, "Mixed Reviews", "Low Reliability"))))) -> Mixed Reviews
A64: =A63+1 -> 63 | B64: 3901 The Alameda, Baltimore, MD 21218 | C64: 39.336145 | D64: -76.596134 | E64: (410) 605-7650 | F64: Loch Raven VA Outpatient Clinic - VA Maryland Health Care System | G64: Listed as "Veterans hospital" on the Google Maps listing; available evidence does not specify eligibility rules, intake procedures, required documents, or referral requirements. | H64: Monday: 8 AM to 4:30 PM; Tuesday: 8 AM to 4:30 PM; Wednesday: 8 AM to 4:30 PM; Thursday: 8 AM to 4:30 PM; Friday: 8 AM to 4:30 PM; Saturday: Closed; Sunday: Closed | I64: Physical & General Health Care | J64: An in-person VA outpatient clinic listed on Google Maps as a veterans hospital / medical clinic at the Loch Raven location in Baltimore that provides outpatient health care services. | L64: Available Google Maps reviewers report positive experiences, citing responsive staff and that they received care. No recurring complaints appear in the visible review text, and the most recent reviews are similarly positive. However, the visible review text sample is small and the official website attribution could not be verified from the provided evidence, so specific service details and eligibility remain insufficiently documented. | M64: 70.624421 | N64: 48.221075 | O64: accepted google identity: 14.2/15; review volume: 20.9/30; review consistency: 7.0/7; review freshness: 4.4/8; verified website: 0.0/15; confirmed irs record: 0.0/20; source corroboration: 1.7/5; Synthesis metadata: insufficient_evidence (not part of numeric confidence) | P64: 8312026 | Q64: =IF(OR(ISBLANK(M64), ISBLANK(N64)), "", IF(N64 < Sheet3!$B$6, "Insufficient Reviews", IF(M64 >= Sheet3!$B$2, "Highly Reliable", IF(M64 >= Sheet3!$B$3, "Reliable", IF(M64 >= Sheet3!$B$4, "Mixed Reviews", "Low Reliability"))))) -> Reliable
A65: =A64+1 -> 64 | B65: 2828 Loch Raven Rd, Baltimore, MD 21218 | C65: 39.322205 | D65: -76.603333 | E65: 410-327-5830 | F65: Beacon of Hope Recovery Community Center | G65: Reviewer reports indicate that visitor authorization and staff interactions have at times limited access; no formal eligibility, intake, or documentation requirements are published in the available sources. | H65: Monday: 8 AM to 4:30 PM; Tuesday: 8 AM to 4:30 PM; Wednesday: 8 AM to 4:30 PM; Thursday: 8 AM to 4:30 PM; Friday: 8 AM to 4:30 PM; Saturday: 8 AM to 4:30 PM; Sunday: 8 AM to 4:30 AM | I65: Other / Uncategorized | J65: A community center at the listed location that, according to Google Maps reviews, accepts clothing donations and distributes donated items to people; at least one reviewer also reports receiving a tax receipt for donations. | L65: Google Maps reviewer text shows mixed experiences: several recent short reviews are positive or neutral, while multiple earlier reviews report negative experiences including staff rudeness, restrictive visitor-authorization practices, and utility/access problems that affected use of services. Review content is limited in detail and the business has not posted responses to reviewer complaints. Overall, available review text is sufficient to show inconsistent user experiences but not to fully corroborate a broad set of service offerings. | M65: 71.129656 | N65: 49.097516 | O65: accepted google identity: 13.5/15; review volume: 25.2/30; review consistency: 1.5/7; review freshness: 7.2/8; verified website: 0.0/15; confirmed irs record: 0.0/20; source corroboration: 1.7/5; Synthesis metadata: insufficient_evidence (not part of numeric confidence) | P65: 8312026 | Q65: =IF(OR(ISBLANK(M65), ISBLANK(N65)), "", IF(N65 < Sheet3!$B$6, "Insufficient Reviews", IF(M65 >= Sheet3!$B$2, "Highly Reliable", IF(M65 >= Sheet3!$B$3, "Reliable", IF(M65 >= Sheet3!$B$4, "Mixed Reviews", "Low Reliability"))))) -> Reliable
A66: =A65+1 -> 65 | B66: 908 Washington Blvd, Baltimore, MD 21230 | C66: 39.28301 | D66: -76.631353 | E66: (410) 624-7554 | F66: SPARC, A Center for Women | G66: Facebook describes the site as a “drop by center,” indicating walk-in/drop-in access; no documented eligibility restrictions, required documents, or referral/intake procedures were found in the available sources. | H66: Monday: 11 AM to 2 PM; Tuesday: 11 AM to 2 PM; Wednesday: 11 AM to 2 PM; Thursday: 11 AM to 2 PM; Friday: Closed; Saturday: Closed; Sunday: Closed | I66: Physical & General Health Care | J66: SPARC is described on its Facebook page and Google Maps listing as a harm-reduction–focused drop-in center and outreach program for women that provides on-site women’s health and supportive services in the Pigtown neighborhood of Baltimore. | K66: https://www.facebook.com/SPARCWomensCenter/ | L66: Public reviews on Google contain a mix of strong praise and at least one recent negative report. Several reviewers describe the center as helpful, supportive, and a meaningful resource for women, while a recent review reports a rude front-desk interaction and difficulty accessing staff during posted hours. The business owner has replied to at least one complaint, indicating some responsiveness to feedback. | M66: 79.873653 | N66: 60.18559 | O66: accepted google identity: 14.2/15; review volume: 20.2/30; review consistency: 1.4/7; review freshness: 6.8/8; verified website: 14.2/15; confirmed irs record: 0.0/20; source corroboration: 3.3/5; Synthesis metadata: high (not part of numeric confidence) | P66: 8312026 | Q66: =IF(OR(ISBLANK(M66), ISBLANK(N66)), "", IF(N66 < Sheet3!$B$6, "Insufficient Reviews", IF(M66 >= Sheet3!$B$2, "Highly Reliable", IF(M66 >= Sheet3!$B$3, "Reliable", IF(M66 >= Sheet3!$B$4, "Mixed Reviews", "Low Reliability"))))) -> Reliable
A67: =A66+1 -> 66 | B67: 1111 Park Ave Apt A, Baltimore, MD 21201 | C67: 39.305478 | D67: -76.621189 | E67: (410) 235-7744 | F67: Youth Empowered Society | G67: Operates a drop-in model serving youth ages 14–25 who are experiencing or at risk of homelessness. Website notes limited storage for personal belongings; no other eligibility, intake, or referral requirements are specified in the available evidence. | H67: Monday: 12:30 to 4 PM; Tuesday: 12:30 to 4 PM; Wednesday: 12:30 to 4 PM; Thursday: 12:30 to 4 PM; Friday: Closed; Saturday: Closed; Sunday: Closed | I67: Youth, Family, & General Support Services | J67: A youth-focused drop-in center that provides basic needs and supportive services for young people, including a safe space, meals and hygiene supplies, clothing and limited storage, individual case management and goal planning, help obtaining IDs and public benefits, employment and education support, and housing-focused referrals and connections to health services. | K67: https://www.yesdropincenter.org/ | L67: Review text was unavailable or too thin to summarize what visitors say about the program, so reviewer themes could not be assessed. Independent corroboration is strong: the organization’s website is reachable and verified against the Google Maps listing, and an IRS record shows a documented reinstatement that supports the organization’s active identity. Structured Google Maps hours and an operational phone number further corroborate a physical drop-in service operating at the listed address. | M67: 69.6 | N67: 70.320068 | O67: accepted google identity: 14.2/15; review volume: 16.8/30; review consistency: 0.0/7; review freshness: 0.0/8; verified website: 14.2/15; confirmed irs record: 20.0/20; source corroboration: 5.0/5; Synthesis metadata: high (not part of numeric confidence) | P67: 8312026 | Q67: =IF(OR(ISBLANK(M67), ISBLANK(N67)), "", IF(N67 < Sheet3!$B$6, "Insufficient Reviews", IF(M67 >= Sheet3!$B$2, "Highly Reliable", IF(M67 >= Sheet3!$B$3, "Reliable", IF(M67 >= Sheet3!$B$4, "Mixed Reviews", "Low Reliability"))))) -> Mixed Reviews
A68: =A67+1 -> 67 | B68: 200 E North Ave, Baltimore, MD 21202 | C68: 39.312156 | D68: -76.613171 | E68: (443) 984-2000 | F68: Baltimore City Public Schools District office | G68: Focus on women & gender-diverse community; call ahead | H68: Monday: 8 AM to 5 PM; Tuesday: 8 AM to 5 PM; Wednesday: 8 AM to 5 PM; Thursday: 8 AM to 5 PM; Friday: 8 AM to 5 PM; Saturday: Closed; Sunday: Closed | I68: Youth, Family, & General Support Services | J68: A Baltimore City Public Schools district administrative office that houses district/board functions and serves families and students seeking district-level assistance; reviewers and official pages indicate the site is used for family engagement and enrollment-related interactions. | K68: http://www.baltimorecityschools.org/ | L68: Google review text shows a mix of experiences: many reviewers praise staff as helpful, pleasant, and the engagement center as professional and efficient, while a separate group report unresponsiveness, disorganization, and long waits for enrollment or homeschool assistance. Recent reviews remain mixed, with both positive reports of quick, welcoming service and ongoing complaints about communication and organization. Official website pages corroborate that this is a district office and include Board Office and family/student-facing content. | M68: 71.876212 | N68: 70.641597 | O68: accepted google identity: 14.2/15; review volume: 30.0/30; review consistency: 0.8/7; review freshness: 8.0/8; verified website: 14.2/15; confirmed irs record: 0.0/20; source corroboration: 3.3/5; Synthesis metadata: high (not part of numeric confidence) | P68: 8312026 | Q68: =IF(OR(ISBLANK(M68), ISBLANK(N68)), "", IF(N68 < Sheet3!$B$6, "Insufficient Reviews", IF(M68 >= Sheet3!$B$2, "Highly Reliable", IF(M68 >= Sheet3!$B$3, "Reliable", IF(M68 >= Sheet3!$B$4, "Mixed Reviews", "Low Reliability"))))) -> Reliable
A69: =A68+1 -> 68 | B69: 226 N Paca St #B, Baltimore, MD 21201 | C69: 39.292623 | D69: -76.622724 | E69: (443) 388-7906 | F69: J.O.Y. Baltimore | G69: The Google Maps listing states services target homeless and displaced young people between ages 12 and 26 and that the organization serves LGBTQIA+ individuals. No intake steps, required documents, referral processes, or other eligibility details were published in the available evidence. | H69: Monday: 10 AM to 5 PM; Tuesday: 10 AM to 5 PM; Wednesday: 10 AM to 5 PM; Thursday: 10 AM to 5 PM; Friday: 10 AM to 5 PM; Saturday: Closed; Sunday: Closed | I69: Youth, Family, & General Support Services | J69: A Baltimore drop-in center serving homeless and displaced youth that, according to its Google Maps profile, provides housing assistance, basic supplies, and youth support services including job help and mentorship. The listing positions the site as a safe, onsite resource for young people and mentions programming and events for children. | K69: https://www.joybaltimore.org/ | L69: Public Google Maps reviewers frequently praise child- and family-focused events and giveaways tied to the organization, describing positive experiences at events (for example, toy distributions and holiday activities). A small number of low-star reviews appear but contain no explanatory text; the visible review text is overwhelmingly positive and the most recent entries remain positive. Web corroboration is limited because the listed website returned an access block (HTTP 403) during scraping, so the Google Maps profile is the primary source for service details. | M69: 73.606547 | N69: 68.305782 | O69: accepted google identity: 14.2/15; review volume: 30.0/30; review consistency: 4.0/7; review freshness: 2.5/8; verified website: 14.2/15; confirmed irs record: 0.0/20; source corroboration: 3.3/5; Synthesis metadata: medium (not part of numeric confidence) | P69: 8312026 | Q69: =IF(OR(ISBLANK(M69), ISBLANK(N69)), "", IF(N69 < Sheet3!$B$6, "Insufficient Reviews", IF(M69 >= Sheet3!$B$2, "Highly Reliable", IF(M69 >= Sheet3!$B$3, "Reliable", IF(M69 >= Sheet3!$B$4, "Mixed Reviews", "Low Reliability"))))) -> Reliable
A70: =A69+1 -> 69 | B70: 7205 Rutherford Rd, Baltimore, MD 21244 | C70: 39.331882 | D70: -76.747515 | E70: (443) 780-1439 | F70: NCIA Youth in Transition School | G70: Admissions require referrals from school systems, interviews with the youth and family, and review by the student's IEP team. Primary service area includes Baltimore County, Baltimore City, and Prince George's County; students may attend from other Maryland school districts. No other eligibility, cost, or documentation details were provided in the available sources. | H70: Monday: 7:45 AM to 3:45 PM; Tuesday: 7:45 AM to 3:45 PM; Wednesday: 7:45 AM to 3:45 PM; Thursday: 7:45 AM to 3:45 PM; Friday: 7:45 AM to 3:45 PM; Saturday: Closed; Sunday: Closed | I70: Employment, Training, & Education | J70: A nonpublic, full-day special education school program serving students with significant barriers (including autism, emotional, and intellectual disabilities). The program provides individualized academic instruction toward a high school diploma or certificate of completion, vocational on- and off-campus job experiences, clinical/therapeutic supports, and behavior-support services. | K70: https://www.ncianet.org/educational-alternatives-for-youth-in-transition/ | L70: There are no public review texts available to summarize user experiences; review feedback was unavailable or too thin to assess satisfaction or recurring themes. Operational signals are present: an active Google Maps listing with published hours and accessibility details and a reachable, corroborating organizational website that describes program offerings and admissions procedures. Because user reviews are absent, claims are based on the organization’s own published materials and the Google listing rather than independent reviewer reports. | M70: 13.5 | N70: 31.833333 | O70: accepted google identity: 14.2/15; review volume: 0.0/30; review consistency: 0.0/7; review freshness: 0.0/8; verified website: 14.2/15; confirmed irs record: 0.0/20; source corroboration: 3.3/5; Synthesis metadata: medium (not part of numeric confidence) | P70: 8312026 | Q70: =IF(OR(ISBLANK(M70), ISBLANK(N70)), "", IF(N70 < Sheet3!$B$6, "Insufficient Reviews", IF(M70 >= Sheet3!$B$2, "Highly Reliable", IF(M70 >= Sheet3!$B$3, "Reliable", IF(M70 >= Sheet3!$B$4, "Mixed Reviews", "Low Reliability"))))) -> Insufficient Reviews
A71: =A70+1 -> 70 | B71: 4623 Falls Rd, Baltimore, MD 21209 | C71: 39.345016 | D71: -76.639785 | E71: (410) 366-1980 | F71: Springboard Community Services | G71: Intake is handled through a Springboard assessment line where a trained specialist evaluates callers and can connect them with a mental health professional and schedule a first appointment during that call. The website and listing indicate appointments are recommended. The site also references crisis and domestic-violence hotlines and suicide/crisis resources for immediate needs. | H71: Monday: 8:30 AM to 4:30 PM; Tuesday: 8:30 AM to 4:30 PM; Wednesday: 8:30 AM to 4:30 PM; Thursday: 8:30 AM to 4:30 PM; Friday: 8:30 AM to 4:30 PM; Saturday: Closed; Sunday: Closed | I71: Youth, Family, & General Support Services | J71: Springboard Community Services operates a Falls Road day center offering behavioral health and related social supports, including counseling and psychiatric services, case management and crisis intervention, and housing-focused case management and assistance for people facing unstable housing. | K71: http://www.springboardmd.org/ | L71: Reviewer comments fetched from the listing emphasize strong, compassionate clinical care and effective case management; several recent comments specifically praise individual staff and report meaningful help from therapy and case management. The small fetched review sample is uniformly positive, but the full public review set on the listing includes several lower-rated entries that were not present in the fetched sample, so negative themes are not visible in the available texts. The newest available reviews remain positive and continue the pattern of praising staff support and clinical outcomes. | M71: 75.267945 | N71: 60.364953 | O71: accepted google identity: 13.4/15; review volume: 16.8/30; review consistency: 7.0/7; review freshness: 6.4/8; verified website: 13.4/15; confirmed irs record: 0.0/20; source corroboration: 3.3/5; Synthesis metadata: high (not part of numeric confidence) | P71: 8312026 | Q71: =IF(OR(ISBLANK(M71), ISBLANK(N71)), "", IF(N71 < Sheet3!$B$6, "Insufficient Reviews", IF(M71 >= Sheet3!$B$2, "Highly Reliable", IF(M71 >= Sheet3!$B$3, "Reliable", IF(M71 >= Sheet3!$B$4, "Mixed Reviews", "Low Reliability"))))) -> Reliable
A72: =A71+1 -> 71 | B72: 2835 Virginia Avenue, Dupont Ave, Baltimore, MD 21215 | C72: 39.34473 | D72: -76.662478 | E72: (443) 429-0215 | F72: Catherine’s Family & Youth Services Inc | G72: Family services are described as available to qualifying low- to no-income families; the website specifies a food and diaper hub, clothing bank, back-to-school drive, and annual holiday giveaways. Youth programs are targeted to young people ages 5–14 who live in the 21215 ZIP code. The organization also states it provides referrals to counseling and housing. (All access/eligibility statements are taken from the cited website and Google Maps listing.) | I72: Youth, Family, & General Support Services | J72: Provides local family- and youth-focused support including a food and diaper pantry, clothing bank, holiday giveaways, and referrals for counseling and housing. Offers youth development programs such as after-school tutoring, homework help, summer camp, and youth support groups, and runs community-focused services including meal delivery for seniors and neighborhood empowerment activities. | K72: http://www.catherinesfamilyandyouthservices.org/ | L72: Public Google Maps reviews consistently describe timely, well-stocked food and diaper distributions and appreciative, helpful volunteers; reviewers repeatedly report receiving food, diapers, clothing, and other essentials. Some reviewers note waits at giveaways (one report of about a two-hour wait), but overall the review text is uniformly positive and the most recent reviews continue that pattern. Website content corroborates the programs and services reviewers describe. | M72: 82.407938 | N72: 73.555276 | O72: accepted google identity: 14.2/15; review volume: 29.8/30; review consistency: 7.0/7; review freshness: 4.9/8; verified website: 14.2/15; confirmed irs record: 0.0/20; source corroboration: 3.3/5; Synthesis metadata: high (not part of numeric confidence) | P72: 8312026 | Q72: =IF(OR(ISBLANK(M72), ISBLANK(N72)), "", IF(N72 < Sheet3!$B$6, "Insufficient Reviews", IF(M72 >= Sheet3!$B$2, "Highly Reliable", IF(M72 >= Sheet3!$B$3, "Reliable", IF(M72 >= Sheet3!$B$4, "Mixed Reviews", "Low Reliability"))))) -> Highly Reliable
A73: =A72+1 -> 72 | B73: 4321 Old York Rd, Baltimore, MD 21212 | C73: 39.342657 | D73: -76.607143 | E73: (410) 433-0426 | F73: The Church Of The Redeemed of The Lord | G73: Website states many services and outreach are offered free of charge. Food pantry is listed on the site as "Wednesday Food Pantry (excluding 1st Wed.) 10:00 AM - 12:30 PM." The site lists service times and recurring programs (e.g., Tuesday night Bible study at 7 PM; Sunday worship at 10 AM; Wednesday prayer 6 PM / Bible study 7 PM) and indicates some activities (e.g., child dedication) require submitting an application. | H73: Monday: Closed; Tuesday: Closed; Wednesday: 10 AM to 12 PM; Thursday: Closed; Friday: 10 AM to 1 PM; Saturday: Closed; Sunday: 10 AM to 1 PM | I73: Youth, Family, & General Support Services | J73: A Pentecostal place of worship that holds regular Sunday services and midweek prayer/Bible-study meetings, operates multiple church ministries and community outreach programs, and runs a Wednesday food pantry/outreach program. | K73: http://www.crlministries.com/ | L73: Public Google Maps reviews in the fetched sample are overwhelmingly positive, with reviewers repeatedly praising the worship experience, the clarity and impact of preaching, the leadership of the senior pastor, and a welcoming congregation. There are no recurring negative themes in the available review text sample, and the newest reviews continue the same positive tone. The organization’s official website corroborates operational programs, service times, ministries, and a food pantry. | M73: 83.857715 | N73: 74.521618 | O73: accepted google identity: 14.2/15; review volume: 30.0/30; review consistency: 4.9/7; review freshness: 7.7/8; verified website: 14.2/15; confirmed irs record: 0.0/20; source corroboration: 3.3/5; Synthesis metadata: high (not part of numeric confidence) | P73: 8312026 | Q73: =IF(OR(ISBLANK(M73), ISBLANK(N73)), "", IF(N73 < Sheet3!$B$6, "Insufficient Reviews", IF(M73 >= Sheet3!$B$2, "Highly Reliable", IF(M73 >= Sheet3!$B$3, "Reliable", IF(M73 >= Sheet3!$B$4, "Mixed Reviews", "Low Reliability"))))) -> Highly Reliable
A74: =A73+1 -> 73 | B74: 2620 Quantico Ave Arlington, Baltimore, MD 21215 | C74: 39.337867 | D74: -76.662074 | E74: (410) 409-7568 | F74: Outcast Food Network | H74: Every 4th Monday of the month starting at 12 p.m. until supplies last | I74: Other / Uncategorized | J74: A physical organization listing on Google Maps for Outcast Food Network at an address in Baltimore; the public listing includes a local contact phone, an associated website URL, and is shown as located within Beacon of Light Citadel of Praise. The listing does not include posted hours or explicit service descriptions, and the linked website page returns an error rather than public program details. | K74: http://outcastfoodnetwork.org/support-the-mission/contact/ | L74: Google Maps has a public listing that identifies the organization and provides a phone contact and location, but there are no user review texts to summarize. The linked website page returned an HTTP 404 at the time of evidence collection, limiting corroboration of programs or schedules. The Maps entry is not marked permanently closed, but overall public information is sparse, so service details could not be confirmed. | M74: 7.5 | N74: 31.833333 | O74: accepted google identity: 14.2/15; review volume: 0.0/30; review consistency: 0.0/7; review freshness: 0.0/8; verified website: 14.2/15; confirmed irs record: 0.0/20; source corroboration: 3.3/5; Synthesis metadata: insufficient_evidence (not part of numeric confidence) | P74: 8312026 | Q74: =IF(OR(ISBLANK(M74), ISBLANK(N74)), "", IF(N74 < Sheet3!$B$6, "Insufficient Reviews", IF(M74 >= Sheet3!$B$2, "Highly Reliable", IF(M74 >= Sheet3!$B$3, "Reliable", IF(M74 >= Sheet3!$B$4, "Mixed Reviews", "Low Reliability"))))) -> Insufficient Reviews
A75: =A74+1 -> 74 | B75: 529 Walker Ave, Baltimore, MD 21212 | C75: 39.371625 | D75: -76.605941 | E75: (410) 900-9111 | F75: RCCG Mercy Court, Baltimore | G75: Worship services: offered in-person and online; kids ministry available (website-stated). Community food outreach: described as served to the Walker Avenue neighborhood five days a week with "no sign-up, no questions asked." No evidence of referral requirements or restricted eligibility was found. | H75: Monday: Closed; Tuesday: Closed; Wednesday: 7 to 8:30 PM; Thursday: Closed; Friday: Closed; Saturday: Closed; Sunday: 10 AM to 12 PM | I75: Youth, Family, & General Support Services | J75: A local Christian church that offers regular in-person and online worship services, midweek Bible study, children’s ministry, corporate prayer gatherings, and community outreach including a recurring free-food distribution to the Walker Avenue neighborhood. | K75: http://www.mercycourt.org/ | L75: Public reviews consistently describe Mercy Court as a welcoming, family-oriented congregation with uplifting worship, interactive Bible study, and active fellowship. Reviewers occasionally highlight positives such as strong praise and worship and accessible online streaming. One recent complaint raised a community-safety concern about a vehicle incident; the listing owner responded publicly. Overall, review text is overwhelmingly positive and the owner appears responsive. | M75: 78.106848 | N75: 89.441038 | O75: accepted google identity: 13.5/15; review volume: 30.0/30; review consistency: 3.0/7; review freshness: 4.5/8; verified website: 13.5/15; confirmed irs record: 20.0/20; source corroboration: 5.0/5; Synthesis metadata: high (not part of numeric confidence) | P75: 8312026 | Q75: =IF(OR(ISBLANK(M75), ISBLANK(N75)), "", IF(N75 < Sheet3!$B$6, "Insufficient Reviews", IF(M75 >= Sheet3!$B$2, "Highly Reliable", IF(M75 >= Sheet3!$B$3, "Reliable", IF(M75 >= Sheet3!$B$4, "Mixed Reviews", "Low Reliability"))))) -> Reliable
A76: =A75+1 -> 75 | B76: 5200 Denmore Ave, Baltimore, MD 21215 | C76: 39.348656 | D76: -76.678205 | E76: (410) 412-4196 | F76: Word & Praise Ministry | H76: Sunday Morning Worship 10am Wednesday Evening Service 7pm | I76: Food & Essential Needs | J76: A local church/ministry that offers regular worship services and church programming with an expressed focus on community outreach and youth. A recent Google Maps review references the organization hosting a free food giveaway / food pantry event. | K76: http://wordandpraisefaithministry.com/ | L76: Public review feedback is very limited. One recent reviewer left a brief positive rating without comment, while another reviewer mentioned missing a service and referenced a Tuesday food giveaway/food pantry event; that recent comment is the primary direct evidence of an outreach food activity. Because the review sample is small and mostly terse, review text alone is thin for judging overall user experience or reliability. | M76: 77.239532 | N76: 55.217992 | O76: accepted google identity: 14.2/15; review volume: 12.3/30; review consistency: 3.5/7; review freshness: 7.6/8; verified website: 14.2/15; confirmed irs record: 0.0/20; source corroboration: 3.3/5; Synthesis metadata: medium (not part of numeric confidence) | P76: 8312026 | Q76: =IF(OR(ISBLANK(M76), ISBLANK(N76)), "", IF(N76 < Sheet3!$B$6, "Insufficient Reviews", IF(M76 >= Sheet3!$B$2, "Highly Reliable", IF(M76 >= Sheet3!$B$3, "Reliable", IF(M76 >= Sheet3!$B$4, "Mixed Reviews", "Low Reliability"))))) -> Reliable
A77: =A76+1 -> 76 | B77: 5011 Arbutus Ave, Baltimore, MD 21215 | C77: 39.342248 | D77: -76.680135 | E77: (443) 759-8921 | F77: Langston Hughes Community, Business & Resource Center | G77: Food pantry attendees are asked to bring their own bags and carts. | H77: Monday: 9 AM to 5 PM; Tuesday: 9 AM to 5 PM; Wednesday: 9 AM to 5 PM; Thursday: 9 AM to 5 PM; Friday: 9 AM to 5 PM; Saturday: Closed; Sunday: Closed | I77: Food & Essential Needs | J77: A community business and resource center that hosts events and venue rentals, operates a recurring food pantry, and connects Park Heights residents to partner-provided supports such as clothing, mental-health, child-care, substance-use, education, and employment resources. | K77: http://langstonhughescbrc.org/ | L77: Google review text and place tags consistently describe the site as hosting a food pantry and community-resource events, and reviewers commonly praise helpful staff, volunteer support, the pantry as a neighborhood lifeline, murals, and the facility’s suitability for events. A small number of brief negative reviews appear but most recent reviews continue to reflect positive experiences and ongoing pantry activity. The center’s own website lists program pages and food‑bank scheduling that corroborate review reports. | M77: 77.917432 | N77: 73.079336 | O77: accepted google identity: 14.2/15; review volume: 30.0/30; review consistency: 3.6/7; review freshness: 7.7/8; verified website: 14.2/15; confirmed irs record: 0.0/20; source corroboration: 3.3/5; Synthesis metadata: high (not part of numeric confidence) | P77: 8312026 | Q77: =IF(OR(ISBLANK(M77), ISBLANK(N77)), "", IF(N77 < Sheet3!$B$6, "Insufficient Reviews", IF(M77 >= Sheet3!$B$2, "Highly Reliable", IF(M77 >= Sheet3!$B$3, "Reliable", IF(M77 >= Sheet3!$B$4, "Mixed Reviews", "Low Reliability"))))) -> Reliable
A78: =A77+1 -> 77 | B78: 5616 Park Heights Ave, Baltimore, MD 21215 | C78: 39.352677 | D78: -76.685322 | E78: (410) 744-5200 | F78: Stepping Stones | H78: Every other Friday from 2 to 3 p.m. or until food is gone | I78: Other / Uncategorized | J78: Appears to operate a physical community organization that provides general help/assistance to people who seek support, based on Google Maps listing details and user comments. Specific programs, eligibility, schedules, and intake procedures are not documented in the available sources. | L78: Available reviewer comments on the Google Maps listing are uniformly positive, with visitors saying they received help and would return. There are no reported problems or negative experiences in the visible comments, but the set of reviewer comments is very small and the most recent comment is dated March 2024. The organization has no verified official website in the provided data and registry matching is unresolved, so the current scope of services and up-to-date operational details are uncertain. | M78: 69.730806 | N78: 32.873372 | O78: accepted google identity: 14.2/15; review volume: 8.5/30; review consistency: 7.0/7; review freshness: 1.5/8; verified website: 0.0/15; confirmed irs record: 0.0/20; source corroboration: 1.7/5; Synthesis metadata: insufficient_evidence (not part of numeric confidence) | P78: 8312026 | Q78: =IF(OR(ISBLANK(M78), ISBLANK(N78)), "", IF(N78 < Sheet3!$B$6, "Insufficient Reviews", IF(M78 >= Sheet3!$B$2, "Highly Reliable", IF(M78 >= Sheet3!$B$3, "Reliable", IF(M78 >= Sheet3!$B$4, "Mixed Reviews", "Low Reliability"))))) -> Insufficient Reviews
A79: =A78+1 -> 78 | B79: 3401 Edgewood Rd, Baltimore, MD 21215 | C79: 39.32612 | D79: -76.673666 | E79: (410) 542-5300 | F79: United House of Prayer - Food Distribution Center | H79: Wednesday from 9 a.m. to 12 p.m. | I79: Food & Essential Needs | J79: A physical food distribution center listed on Google Maps as a food bank that appears to provide in-person food distribution at the listed address. | L79: Public review text was unavailable or too thin, so reviewers’ experiences cannot be summarized from text. The Google Maps listing explicitly labels the location as a food bank and provides a phone number plus accessibility details, which supports the presence of an in-person food distribution site at this address. The organization’s website could not be reliably attributed and no registry match was found, so identity and broader program details are not corroborated by other sources. | M79: 73.008558 | N79: 35.05854 | O79: accepted google identity: 14.2/15; review volume: 8.5/30; review consistency: 7.0/7; review freshness: 3.7/8; verified website: 0.0/15; confirmed irs record: 0.0/20; source corroboration: 1.7/5; Synthesis metadata: insufficient_evidence (not part of numeric confidence) | P79: 8312026 | Q79: =IF(OR(ISBLANK(M79), ISBLANK(N79)), "", IF(N79 < Sheet3!$B$6, "Insufficient Reviews", IF(M79 >= Sheet3!$B$2, "Highly Reliable", IF(M79 >= Sheet3!$B$3, "Reliable", IF(M79 >= Sheet3!$B$4, "Mixed Reviews", "Low Reliability"))))) -> Insufficient Reviews
A80: =A79+1 -> 79 | B80: 624 Gutman Ave, Baltimore, MD 21218 | C80: 39.317555 | D80: -76.606769 | E80: 443-842-4037 | F80: Donald Bentley Food Pantry | G80: New pantry clients are asked to provide their name, an address, and household size at intake. Once registered, clients may pick up food every other week (two times per month). Visitors are asked to bring their own bag. (Intake and scheduling information published on the pantry website.) | H80: Monday: Closed; Tuesday: Closed; Wednesday: Closed; Thursday: Closed; Friday: Closed; Saturday: 9 AM to 12 PM; Sunday: Closed | I80: Food & Essential Needs | J80: A community food pantry in East Baltimore that distributes a balanced selection of grocery items (including meat, milk, fruit, vegetables, bread, and pantry staples) to local residents on a weekly Saturday distribution. The pantry is run by volunteers and sets up so visitors can choose among available food options. | K80: https://www.dbfpbaltimore.org/ | L80: Google reviewers consistently praise the pantry for offering fresh produce, meat, dairy, and sufficient quantities for families, and they describe staff and volunteers as generally friendly and helpful. A small number of reviewers report occasional negative interactions with individual volunteers or rude behavior, but most recent reviews continue to emphasize the positive experience and freshness of the food. The pantry also publishes a website with matching hours, intake instructions, and volunteer/donation information that corroborates the listing. | M80: 79.602139 | N80: 69.983244 | O80: accepted google identity: 13.5/15; review volume: 26.4/30; review consistency: 7.0/7; review freshness: 6.2/8; verified website: 13.5/15; confirmed irs record: 0.0/20; source corroboration: 3.3/5; Synthesis metadata: high (not part of numeric confidence) | P80: 8312026 | Q80: =IF(OR(ISBLANK(M80), ISBLANK(N80)), "", IF(N80 < Sheet3!$B$6, "Insufficient Reviews", IF(M80 >= Sheet3!$B$2, "Highly Reliable", IF(M80 >= Sheet3!$B$3, "Reliable", IF(M80 >= Sheet3!$B$4, "Mixed Reviews", "Low Reliability"))))) -> Reliable
A81: =A80+1 -> 80 | B81: 721 E 25th St, Baltimore, MD 21218 | C81: 39.318207 | D81: -76.60311 | E81: (443) 449-0933 | F81: Spirit Of Faith Deliverance Church | H81: Monday: Closed; Tuesday: 7:30 to 9 PM; Wednesday: Closed; Thursday: Closed; Friday: 7:30 to 10:30 PM; Saturday: Closed; Sunday: 10:30 AM to 3 PM | I81: Food & Essential Needs | J81: A local church that holds regular worship services and community outreach; Google Maps reviews indicate staff/leadership have provided food assistance to individuals and run occasional food/meat giveaway events. | K81: https://tmeela.wixsite.com/spiritoffaithdeliver | L81: Google Maps reviewers repeatedly describe a welcoming, nonjudgmental church atmosphere and single out the pastor and leadership as personally supportive; several recent reviews specifically recount receiving food assistance or mention a monthly food/meat giveaway. Negative or neutral feedback is limited in number (one reviewer described attending a funeral) and does not contradict the pattern of community outreach described by other reviewers. Review text is available and relatively recent, supporting the summary. | M81: 82.665167 | N81: 62.289842 | O81: accepted google identity: 14.2/15; review volume: 20.2/30; review consistency: 4.2/7; review freshness: 6.1/8; verified website: 14.2/15; confirmed irs record: 0.0/20; source corroboration: 3.3/5; Synthesis metadata: medium (not part of numeric confidence) | P81: 8312026 | Q81: =IF(OR(ISBLANK(M81), ISBLANK(N81)), "", IF(N81 < Sheet3!$B$6, "Insufficient Reviews", IF(M81 >= Sheet3!$B$2, "Highly Reliable", IF(M81 >= Sheet3!$B$3, "Reliable", IF(M81 >= Sheet3!$B$4, "Mixed Reviews", "Low Reliability"))))) -> Highly Reliable
A82: =A81+1 -> 81 | B82: 116 W Pennsylvania Ave, Towson, MD 21204 | C82: 39.401391 | D82: -76.606458 | E82: (410) 296-4855 | F82: Assistance Center of Towson Churches (ACTC) | G82: Food: groceries available every two weeks to people living in ACTC's service area; grocery pickup hours include Monday–Friday 10:00 a.m. to 2:00 p.m. and Wednesdays 4:00 p.m. to 7:00 p.m. (website). Emergency financial assistance: requests must be submitted via the organization's online jotform (no in-person meetings); volunteers are available to process requests on Tuesday/Wednesday/Thursday from 10:00 a.m. to 2:00 p.m. Assistance is limited to specified ZIP codes and is available one time only; applicants who received assistance since October 2020 are ineligible to receive additional help (website). | H82: Monday: 10 AM to 2 PM; Tuesday: 10 AM to 2 PM; Wednesday: 10 AM to 2 PM; Thursday: 10 AM to 2 PM; Friday: 10 AM to 2 PM; Saturday: Closed; Sunday: Closed | I82: Food & Essential Needs | J82: A community assistance center that provides grocery distribution and meal services, limited emergency financial help for rental eviction or utility (BGE) bills, and referrals/limited homeless-support services (toiletries, weekend food, clothing referrals, and mail pickup) through partner organizations. | K82: http://www.actcserves.org/ | L82: Google Maps reviewers repeatedly praise the staff and volunteers as friendly and helpful, and multiple reviewers specifically mention receiving food or rent assistance. Recurring concerns in the reviews include communication issues (a voicemail reported full) and uncertainty or delays in the application/process for rental assistance. The most recent reviews remain largely positive while a small number of reviewers report trouble with contacting or receiving timely updates from the center. | M82: 76.642411 | N82: 70.363378 | O82: accepted google identity: 14.2/15; review volume: 30.0/30; review consistency: 2.1/7; review freshness: 6.4/8; verified website: 14.2/15; confirmed irs record: 0.0/20; source corroboration: 3.3/5; Synthesis metadata: high (not part of numeric confidence) | P82: 8312026 | Q82: =IF(OR(ISBLANK(M82), ISBLANK(N82)), "", IF(N82 < Sheet3!$B$6, "Insufficient Reviews", IF(M82 >= Sheet3!$B$2, "Highly Reliable", IF(M82 >= Sheet3!$B$3, "Reliable", IF(M82 >= Sheet3!$B$4, "Mixed Reviews", "Low Reliability"))))) -> Reliable
A83: =A82+1 -> 82 | B83: 1407 Bolton St, Baltimore, MD 21217 | C83: 39.306466 | D83: -76.624953 | E83: (410) 669-1229 | F83: Samaritan Community | G83: Services are for individuals and families in Baltimore City; new visitors are interviewed by the Program Director and receive a personalized plan. Clothing shop use requires an appointment. Pantry hours and other program details are provided by phone; some pantry services are delivered to members' homes. (All access details are taken from the organization website and the Google Maps listing.) | H83: the third Saturday of the month from 9 to 11:30 a.m. | I83: Food & Essential Needs | J83: A Baltimore City community organization that provides crisis-intervention supports and longer-term empowerment services, including a food pantry, a free clothing and household goods shop, case management, emergency financial stipends, counseling, and related enrichment activities. | K83: https://www.samaritancommunity.org/ | L83: Google reviewers repeatedly report staff are helpful and caring and describe receiving food, clothing, and emergency financial help (including utility and rent-related assistance) as well as support for job-interview needs. There are very few negative comments in the review text sample and reviewers’ accounts emphasize the organization’s direct, practical assistance. The most recent reviews continue the same positive themes. | M83: 81.98483 | N83: 74.708174 | O83: accepted google identity: 14.2/15; review volume: 30.0/30; review consistency: 6.0/7; review freshness: 6.9/8; verified website: 14.2/15; confirmed irs record: 0.0/20; source corroboration: 3.3/5; Synthesis metadata: high (not part of numeric confidence) | P83: 8312026 | Q83: =IF(OR(ISBLANK(M83), ISBLANK(N83)), "", IF(N83 < Sheet3!$B$6, "Insufficient Reviews", IF(M83 >= Sheet3!$B$2, "Highly Reliable", IF(M83 >= Sheet3!$B$3, "Reliable", IF(M83 >= Sheet3!$B$4, "Mixed Reviews", "Low Reliability"))))) -> Reliable
A84: =A83+1 -> 83 | B84: 1542 N Gilmor St, Baltimore, MD 21217 | C84: 39.306343 | D84: -76.643767 | E84: (410) 523-0061 | F84: St.Gregory the Great Catholic Church - Food Distribution Center | G84: Reviewers report the pantry conducts food distribution events on Mondays and Thursdays (review text). The site has a wheelchair-accessible parking lot. No other eligibility, documentation, intake, or referral requirements were documented in the available evidence. | H84: Monday from 10 a.m. to 2 p.m. & Thursday from 10 a.m. to 2 p.m., by appointment only. Requests for food are not accepted through email. Call for appointment. | I84: Food & Essential Needs | J84: A local food distribution/pantry operating from a site associated with St. Gregory the Great that provides food to people in the community (listed as a food bank/food distribution center on its Google Maps profile). | L84: Google Maps reviewers consistently describe friendly, helpful staff and a dependable, positive local food distribution operation; several recent comments explicitly reference food distributions. There are few substantive negative comments in the fetched review sample, and the newest reviews continue the same positive tone. Public website attribution failed and there are no structured Google Maps opening hours, so some operational details are not corroborated by an official site listing. | M84: 79.10469 | N84: 49.103362 | O84: accepted google identity: 14.2/15; review volume: 20.5/30; review consistency: 5.8/7; review freshness: 6.9/8; verified website: 0.0/15; confirmed irs record: 0.0/20; source corroboration: 1.7/5; Synthesis metadata: medium (not part of numeric confidence) | P84: 8312026 | Q84: =IF(OR(ISBLANK(M84), ISBLANK(N84)), "", IF(N84 < Sheet3!$B$6, "Insufficient Reviews", IF(M84 >= Sheet3!$B$2, "Highly Reliable", IF(M84 >= Sheet3!$B$3, "Reliable", IF(M84 >= Sheet3!$B$4, "Mixed Reviews", "Low Reliability"))))) -> Reliable
A85: =A84+1 -> 84 | B85: 1609 Druid Hill Ave, Baltimore, MD 21217 | C85: 39.30487 | D85: -76.631719 | E85: (410) 728-1600 | F85: Druid Hill YMCA | G85: Many classes are open to Y members; some classes require tokens that are distributed at family centers after scanning in (tokens available no earlier than 30 minutes before class). The site lists separate "Stay & Play" hours for family center childcare and specific scheduled hours for the Y Fresh Mart ( Fresh Mart operates on limited days/times). | H85: Monday: 6 AM to 9 PM; Tuesday: 6 AM to 9 PM; Wednesday: 6 AM to 9 PM; Thursday: 6 AM to 9 PM; Friday: 6 AM to 9 PM; Saturday: 8 AM to 5 PM; Sunday: Closed | I85: Physical & General Health Care | J85: A Y (YMCA) family center at Druid Hill that operates a gym and fitness facility and offers member fitness programming (group exercise, small-group training, and personal training), swim and water-exercise lessons, therapeutic-exercise programs, and an on-site Y Fresh Mart market with limited hours. | K85: https://ymaryland.org/locations/druidhilly | L85: Google reviewers consistently mention good customer service, a clean and pleasant atmosphere, and that the facility is a solid community-centered place to exercise. A few reviewers raise cost concerns about membership pricing, but most recent reviews show the same generally positive tone. The facility's Google listing and the organization's location page corroborate published hours, on-site programs, and the presence of a Fresh Mart. | M85: 79.106719 | N85: 73.578469 | O85: accepted google identity: 14.2/15; review volume: 30.0/30; review consistency: 3.9/7; review freshness: 7.9/8; verified website: 14.2/15; confirmed irs record: 0.0/20; source corroboration: 3.3/5; Synthesis metadata: high (not part of numeric confidence) | P85: 8312026 | Q85: =IF(OR(ISBLANK(M85), ISBLANK(N85)), "", IF(N85 < Sheet3!$B$6, "Insufficient Reviews", IF(M85 >= Sheet3!$B$2, "Highly Reliable", IF(M85 >= Sheet3!$B$3, "Reliable", IF(M85 >= Sheet3!$B$4, "Mixed Reviews", "Low Reliability"))))) -> Reliable
A86: =A85+1 -> 85 | B86: 47950 Mattapany Rd, Lexington Park, MD 20653 | C86: 38.191144 | D86: -76.416804 | E86: (301) 862-4600 | F86: St. Cecilia Catholic Church | H86: Monday: Closed; Tuesday: 9 AM to 2 PM; Wednesday: 9 AM to 2 PM; Thursday: 9 AM to 2 PM; Friday: 9 AM to 2 PM; Saturday: Closed; Sunday: Closed | I86: Food & Essential Needs | J86: A parish-run food pantry / food distribution program that provides non-perishable groceries and hygiene/household items to people in need from a physical location at the church. | K86: http://www.stceciliamd.org/ | L86: Public Google Maps reviewers give the listing high ratings, but the fetched review sample contains only star ratings with no written comments, so reviewer feedback about user experience is unavailable or too thin to identify recurring themes. The organization’s official website explicitly lists a Food Pantry and item types requested (non-perishables and hygiene products), and the site and Google listing include contact details and published hours, corroborating that a physical food distribution service operates at this location. Because textual review detail is minimal, wider user-experience conclusions cannot be confidently drawn from reviews alone. | M86: 79.997285 | N86: 64.643288 | O86: accepted google identity: 14.2/15; review volume: 20.4/30; review consistency: 7.0/7; review freshness: 5.4/8; verified website: 14.2/15; confirmed irs record: 0.0/20; source corroboration: 3.3/5; Synthesis metadata: medium (not part of numeric confidence) | P86: 8312026 | Q86: =IF(OR(ISBLANK(M86), ISBLANK(N86)), "", IF(N86 < Sheet3!$B$6, "Insufficient Reviews", IF(M86 >= Sheet3!$B$2, "Highly Reliable", IF(M86 >= Sheet3!$B$3, "Reliable", IF(M86 >= Sheet3!$B$4, "Mixed Reviews", "Low Reliability"))))) -> Reliable
A87: =A86+1 -> 86 | B87: 2201 Garrison Blvd, Baltimore, MD 21216 | C87: 39.312385 | D87: -76.675065 | E87: (410) 945-3575 | F87: Mount Moriah Baptist Church - Food Distribution Center | G87: The listing indicates there is an eligibility requirement but does not specify the criteria, required documents, or intake/referral process; confirm eligibility and intake requirements with the provider. | H87: Monday: Closed; Tuesday: 8:30 to 10 AM; Wednesday: Closed; Thursday: Closed; Friday: 8:30 to 10 AM; Saturday: Closed; Sunday: Closed | I87: Food & Essential Needs | J87: A church-based food distribution center that offers on-site food pantry services and provides grocery pickup and delivery options according to its Google Maps listing. | L87: There are no public Google reviews or review text available for this listing, so direct user-feedback about service quality is unavailable. The Google listing does provide a phone number and structured hours, which supports that the location is active, but independent corroboration beyond the Google entry is limited. | M87: 9 | N87: 15.916667 | O87: accepted google identity: 14.2/15; review volume: 0.0/30; review consistency: 0.0/7; review freshness: 0.0/8; verified website: 0.0/15; confirmed irs record: 0.0/20; source corroboration: 1.7/5; Synthesis metadata: insufficient_evidence (not part of numeric confidence) | P87: 8312026 | Q87: =IF(OR(ISBLANK(M87), ISBLANK(N87)), "", IF(N87 < Sheet3!$B$6, "Insufficient Reviews", IF(M87 >= Sheet3!$B$2, "Highly Reliable", IF(M87 >= Sheet3!$B$3, "Reliable", IF(M87 >= Sheet3!$B$4, "Mixed Reviews", "Low Reliability"))))) -> Insufficient Reviews
A88: =A87+1 -> 87 | B88: 3200 Walbrook Ave, Baltimore, MD 21216 | C88: 39.310215 | D88: -76.671274 | E88: (410) 383-9633 | F88: Trinity Presbyterian Church | G88: For more information about the pantry or to inquire about accessing services, contact the church office at (410) 383-9633 (as listed on the organization's website). | H88: The Food Pantry is open the last 2 Saturdays of the month. Hours of service are 10:00 am - 12:00 pm | I88: Food & Essential Needs | J88: Trinity Presbyterian Church operates a community food pantry (The Nancy Bennett Food Pantry) that provides scheduled in-person food distribution at the church location in the Walbrook neighborhood of Baltimore. | K88: https://www.trinitypresbalt.org/ | L88: The organization's official website explicitly describes and schedules the Nancy Bennett Food Pantry and gives a local contact number. A single recent Google review (sample) praises the congregation s neighborhood presence and mentions a pantry schedule; however, review feedback is extremely limited (one recent sample) so it is too thin to generalize about client experiences or service consistency. Website and map listings corroborate the existence of the pantry, though minor differences appear between the review text and the website about which Saturdays are used for distribution. | M88: 78.114167 | N88: 43.776112 | O88: accepted google identity: 14.2/15; review volume: 1.2/30; review consistency: 7.0/7; review freshness: 3.7/8; verified website: 14.2/15; confirmed irs record: 0.0/20; source corroboration: 3.3/5; Synthesis metadata: medium (not part of numeric confidence) | P88: 8312026 | Q88: =IF(OR(ISBLANK(M88), ISBLANK(N88)), "", IF(N88 < Sheet3!$B$6, "Insufficient Reviews", IF(M88 >= Sheet3!$B$2, "Highly Reliable", IF(M88 >= Sheet3!$B$3, "Reliable", IF(M88 >= Sheet3!$B$4, "Mixed Reviews", "Low Reliability"))))) -> Reliable
A89: =A88+1 -> 88 | B89: 5204 Liberty Heights Ave, Baltimore, MD 21207 | C89: 39.333834 | D89: -76.702051 | E89: (410) 367-1117 | F89: Concord Baptist Church - Food Distribution Center | G89: Proof of residence and photo ID. | H89: Tue: 8:30AM-10AM Fri: 8:30AM-10AM | I89: Food & Essential Needs | J89: A physical site listed on Google Maps as a food distribution center / food bank serving the local Baltimore neighborhood. | L89: Google Maps reviewers in the fetched sample are uniformly positive, with three recent 5-star ratings; the written comments are very short and provide little operational detail beyond a generally favorable impression. There are no negative reviews in the sample, but the small number of reviews and sparse text limit confidence about routine availability, eligibility rules, or schedules. Attempts to verify an official website failed and no registry match was found, so online corroboration beyond the Google listing is limited. | M89: 78.813952 | N89: 41.718159 | O89: accepted google identity: 14.2/15; review volume: 11.3/30; review consistency: 7.0/7; review freshness: 7.5/8; verified website: 0.0/15; confirmed irs record: 0.0/20; source corroboration: 1.7/5; Synthesis metadata: insufficient_evidence (not part of numeric confidence) | P89: 8312026 | Q89: =IF(OR(ISBLANK(M89), ISBLANK(N89)), "", IF(N89 < Sheet3!$B$6, "Insufficient Reviews", IF(M89 >= Sheet3!$B$2, "Highly Reliable", IF(M89 >= Sheet3!$B$3, "Reliable", IF(M89 >= Sheet3!$B$4, "Mixed Reviews", "Low Reliability"))))) -> Reliable
A90: =A89+1 -> 89 | B90: 3001 Baker St, Baltimore, MD 21216 | C90: 39.305694 | D90: -76.667623 | E90: (410) 947-1863 | F90: Whitestone Baptist Church | G90: none specified | H90: Monday: Closed; Tuesday: 9 AM to 3:30 PM; Wednesday: 9 AM to 3:30 PM; Thursday: 9 AM to 3:30 PM; Friday: 9 AM to 3:30 PM; Saturday: Closed; Sunday: Closed | I90: Food & Essential Needs | J90: Operates an on-site food distribution (food pantry) that provides packaged food to community members through in-person distribution sessions. | L90: Local reviewers consistently report positive experiences with the site’s food distribution, describing helpful, polite staff and advising attendees to arrive early on distribution days. There are no recurring complaints in the fetched review sample; the most recent reviews remain positive and align with earlier feedback. A verified official website was not found in the available evidence, so online corroboration is limited to the map listing and reviewer reports. | M90: 76.677574 | N90: 55.043113 | O90: accepted google identity: 14.2/15; review volume: 26.4/30; review consistency: 5.8/7; review freshness: 7.0/8; verified website: 0.0/15; confirmed irs record: 0.0/20; source corroboration: 1.7/5; Synthesis metadata: medium (not part of numeric confidence) | P90: 8312026 | Q90: =IF(OR(ISBLANK(M90), ISBLANK(N90)), "", IF(N90 < Sheet3!$B$6, "Insufficient Reviews", IF(M90 >= Sheet3!$B$2, "Highly Reliable", IF(M90 >= Sheet3!$B$3, "Reliable", IF(M90 >= Sheet3!$B$4, "Mixed Reviews", "Low Reliability"))))) -> Reliable
A91: =A90+1 -> 90 | B91: 1020 W Lafayette Ave, Baltimore, MD 21217 | C91: 39.298957 | D91: -76.635665 | E91: (410) 523-4588 | F91: St. James Episcopal Church | G91: Website invitation to worship is stated on the site; Google Maps listing indicates wheelchair-accessible entrance, parking, and a wheelchair-accessible restroom. No eligibility rules, intake, referral, ID, or document requirements were evidenced. | H91: Worship with us every Sunday Morning at 9:30 | I91: Other / Uncategorized | J91: An Episcopal church that holds regular worship services at its Baltimore location and maintains an accessible church building. Public-facing information available online describes Sunday worship and contact details; no independent, evidence-backed information about a food pantry or other social-service programs was found in the supplied sources. | K91: http://www.stjamesonthesquare.org/ | L91: Google Maps reviewers commonly praise the church itself and its historic character, and several reviewers explicitly recommend visiting. A recurring negative note in the textual reviews mentions lack of an indoor restroom; otherwise reviewers who left text are briefly positive. The most recent reviews in the fetched sample are largely positive but often contain no text, and the listing owner has not posted responses in the available review sample. | M91: 71.834387 | N91: 72.416215 | O91: accepted google identity: 14.2/15; review volume: 30.0/30; review consistency: 3.0/7; review freshness: 7.6/8; verified website: 14.2/15; confirmed irs record: 0.0/20; source corroboration: 3.3/5; Synthesis metadata: medium (not part of numeric confidence) | P91: 8312026 | Q91: =IF(OR(ISBLANK(M91), ISBLANK(N91)), "", IF(N91 < Sheet3!$B$6, "Insufficient Reviews", IF(M91 >= Sheet3!$B$2, "Highly Reliable", IF(M91 >= Sheet3!$B$3, "Reliable", IF(M91 >= Sheet3!$B$4, "Mixed Reviews", "Low Reliability"))))) -> Reliable
A92: =A91+1 -> 91 | B92: 8240 Loch Raven Blvd, Towson, MD 21286 | C92: 39.389091 | D92: -76.572278 | E92: (410) 825-3314 | F92: Babcock Presbyterian Church | G92: The congregation states it "opens our doors to all." Bible Study and Prayer meetings are offered via Zoom (website indicates a weekly Wednesday meeting and that a Meeting ID/passcode may be required and is provided on the site). No other eligibility, intake, or referral requirements are documented in the provided evidence. | H92: Monday: 9 AM to 5 PM; Tuesday: 9 AM to 5 PM; Wednesday: 9 AM to 5 PM; Thursday: 9 AM to 5 PM; Friday: 9 AM to 5 PM; Saturday: 9 AM to 5 PM; Sunday: 9 AM to 5 PM | I92: Food & Essential Needs | J92: A local Presbyterian congregation that holds regular worship services, runs Bible study and prayer meetings (including a Wednesday evening Zoom meeting), streams services and events online, and operates a food ministry/food pantry serving the surrounding community. | K92: http://www.babcockpc.org/ | L92: Google Maps reviewers frequently describe the church as welcoming and like a family, and longtime attendees report positive, personal experiences with the congregation. Reviewers also mention the pleasant facility and convenient location, and several note the church offers meetings and streamed services. Feedback about community service (notably the food pantry) appears in reviews but is limited and somewhat mixed in tone; overall, the newest reviews continue to reflect a positive impression of the congregation and its activities. | M92: 79.600917 | N92: 70.438092 | O92: accepted google identity: 14.2/15; review volume: 28.6/30; review consistency: 2.6/7; review freshness: 7.4/8; verified website: 14.2/15; confirmed irs record: 0.0/20; source corroboration: 3.3/5; Synthesis metadata: high (not part of numeric confidence) | P92: 8312026 | Q92: =IF(OR(ISBLANK(M92), ISBLANK(N92)), "", IF(N92 < Sheet3!$B$6, "Insufficient Reviews", IF(M92 >= Sheet3!$B$2, "Highly Reliable", IF(M92 >= Sheet3!$B$3, "Reliable", IF(M92 >= Sheet3!$B$4, "Mixed Reviews", "Low Reliability"))))) -> Reliable
A93: =A92+1 -> 92 | B93: 1300 N Eden St, Baltimore, MD 21213 | C93: 39.305351 | D93: -76.599783 | E93: (410) 385-0900 | F93: Knox Presbyterian Church | G93: none noted | H93: 3rd Sat 9am-12pm | I93: Other / Uncategorized | J93: A Presbyterian church at a physical location in Baltimore that maintains a published phone number and website; the site references ongoing ministries and weekly worship but does not list specific social programs or service details. | K93: http://knoxpcbaltimore.com/ | L93: Google Maps reviewers give consistently positive ratings and the most recent reviews remain favorable; the one written comment in the fetched sample praises the service. Most of the fetched reviews contain no written text, so detailed qualitative information about visitor experiences and specific programs is limited. The listing shows a valid phone number and website, and the owner has not posted responses to the sampled reviews. | M93: 73.420015 | N93: 68.589344 | O93: accepted google identity: 14.2/15; review volume: 23.8/30; review consistency: 5.6/7; review freshness: 7.4/8; verified website: 14.2/15; confirmed irs record: 0.0/20; source corroboration: 3.3/5; Synthesis metadata: medium (not part of numeric confidence) | P93: 8312026 | Q93: =IF(OR(ISBLANK(M93), ISBLANK(N93)), "", IF(N93 < Sheet3!$B$6, "Insufficient Reviews", IF(M93 >= Sheet3!$B$2, "Highly Reliable", IF(M93 >= Sheet3!$B$3, "Reliable", IF(M93 >= Sheet3!$B$4, "Mixed Reviews", "Low Reliability"))))) -> Reliable
A94: =A93+1 -> 93 | B94: 817 N Mount St, Baltimore, MD 21217 | C94: 39.298339 | D94: -76.644124 | E94: (410) 523-9082 | F94: New Mt Zion Baptist Church | G94: none noted | H94: The 2nd & 4th Saturday of the month from 10 a.m. to 12 p.m. at Chapel located behind the main church building. | I94: Food & Essential Needs | J94: A church location that operates an on-site food distribution/food pantry (listed as New Mount Zion Outreach - Food Distribution Center at the church address). | L94: Public Google Maps reviews are largely positive, with recurring praise for the pastor, friendly congregation, and community involvement. A small number of lower-rated reviews appear but commonly lack explanatory text; the newest reviews remain positive. The primary corroborating evidence is the Google Maps listing; no verified website or registry match was found, so external corroboration is limited. | M94: 72.67819 | N94: 54.024389 | O94: accepted google identity: 14.2/15; review volume: 28.3/30; review consistency: 4.0/7; review freshness: 5.9/8; verified website: 0.0/15; confirmed irs record: 0.0/20; source corroboration: 1.7/5; Synthesis metadata: medium (not part of numeric confidence) | P94: 8312026 | Q94: =IF(OR(ISBLANK(M94), ISBLANK(N94)), "", IF(N94 < Sheet3!$B$6, "Insufficient Reviews", IF(M94 >= Sheet3!$B$2, "Highly Reliable", IF(M94 >= Sheet3!$B$3, "Reliable", IF(M94 >= Sheet3!$B$4, "Mixed Reviews", "Low Reliability"))))) -> Reliable
A95: =A94+1 -> 94 | B95: 1401 N Milton Ave, Baltimore, MD 21213 | C95: 39.307266 | D95: -76.582519 | E95: (443) 756-8162 | F95: Angels Helping Angels | G95: none noted | H95: the third Saturday of the month from 10:30 am–12:30 pm | I95: Food & Essential Needs | J95: A local Baltimore organization that operates a food pantry/food distribution and, according to its website, provides housing-related support, clothing distribution, monetary (cash) assistance, and referral help to individuals and families in need. | K95: http://ahamd.org/index.php/contact-us | L95: Public review text is unavailable (the Google Maps listing has a single review with no written feedback), so there is no usable reviewer narrative to summarize. The organization’s official website is reachable and describes food distribution plus housing, clothing, monetary support, and referral services, and the Google Maps listing is active; however, the listing and website do not publish clear, up-to-date hours, intake steps, or documented eligibility requirements online. Because public review feedback is too thin and operational details are limited on the public pages, external confirmation of current day-to-day access is constrained. | M95: 76.934668 | N95: 45.152541 | O95: accepted google identity: 14.2/15; review volume: 5.0/30; review consistency: 7.0/7; review freshness: 1.3/8; verified website: 14.2/15; confirmed irs record: 0.0/20; source corroboration: 3.3/5; Synthesis metadata: medium (not part of numeric confidence) | P95: 8312026 | Q95: =IF(OR(ISBLANK(M95), ISBLANK(N95)), "", IF(N95 < Sheet3!$B$6, "Insufficient Reviews", IF(M95 >= Sheet3!$B$2, "Highly Reliable", IF(M95 >= Sheet3!$B$3, "Reliable", IF(M95 >= Sheet3!$B$4, "Mixed Reviews", "Low Reliability"))))) -> Reliable
A96: =A95+1 -> 95 | B96: 230 N Fulton Ave, Baltimore, MD 21223 | C96: 39.291494 | D96: -76.645609 | E96: (410) 945-7923 | F96: People's Church of Baltimore | G96: Wheelchair-accessible parking available; on-site restroom. | H96: 10am-12pm Wed-Sat | I96: Other / Uncategorized | J96: A Baptist church listed at 230 N Fulton Ave in Baltimore; the public listing identifies it as a local Baptist congregation and indicates on-site accessibility and restroom amenities. | L96: The primary public listing (Google Maps) identifies this location as a Baptist church and shows basic amenities, but no review text was fetched to describe visitor experiences. The organization’s claimed website could not be verified and there is no matching IRS nonprofit record in the available registry data, so independent corroboration is limited. | M96: 62.7 | N96: 25.815597 | O96: accepted google identity: 14.2/15; review volume: 9.9/30; review consistency: 0.0/7; review freshness: 0.0/8; verified website: 0.0/15; confirmed irs record: 0.0/20; source corroboration: 1.7/5; Synthesis metadata: insufficient_evidence (not part of numeric confidence) | P96: 8312026 | Q96: =IF(OR(ISBLANK(M96), ISBLANK(N96)), "", IF(N96 < Sheet3!$B$6, "Insufficient Reviews", IF(M96 >= Sheet3!$B$2, "Highly Reliable", IF(M96 >= Sheet3!$B$3, "Reliable", IF(M96 >= Sheet3!$B$4, "Mixed Reviews", "Low Reliability"))))) -> Insufficient Reviews
A97: =A96+1 -> 96 | B97: 7200 Harford Rd, Baltimore, MD 21234 | C97: 39.368309 | D97: -76.547866 | E97: (410) 444-1595 | F97: friendship outreach center | G97: Offers referrals and limited financial assistance for clients facing eviction and BGE turnoffs when funding is available. Serves people described as “in need.” No other eligibility, documentation, intake, or referral requirements are stated in the available evidence. | H97: Monday: Closed; Tuesday: 10 to 11:30 AM; Wednesday: 10 to 11:30 AM; Thursday: 10 to 11:30 AM; Friday: Closed; Saturday: Closed; Sunday: Closed | I97: Food & Essential Needs | J97: A community-based food hub that distributes free food to people in need and provides referrals; when funding is available it also offers limited financial assistance to clients facing eviction and BGE utility turnoffs. | L97: Google Maps reviewers repeatedly praise the staff’s kindness and helpfulness and report receiving useful food assistance. Several recent reviews echo those positive experiences. A minority of reviewers report inconsistent hours or arriving when the organization appeared closed despite posted times, indicating occasional reliability issues. | M97: 76.398201 | N97: 56.334292 | O97: accepted google identity: 14.2/15; review volume: 29.6/30; review consistency: 3.2/7; review freshness: 7.6/8; verified website: 0.0/15; confirmed irs record: 0.0/20; source corroboration: 1.7/5; Synthesis metadata: medium (not part of numeric confidence) | P97: 8312026 | Q97: =IF(OR(ISBLANK(M97), ISBLANK(N97)), "", IF(N97 < Sheet3!$B$6, "Insufficient Reviews", IF(M97 >= Sheet3!$B$2, "Highly Reliable", IF(M97 >= Sheet3!$B$3, "Reliable", IF(M97 >= Sheet3!$B$4, "Mixed Reviews", "Low Reliability"))))) -> Reliable
A98: =A97+1 -> 97 | B98: 2031 W Baltimore St, Baltimore, MD 21223 | C98: 39.287728 | D98: -76.649757 | E98: (410) 233-8558 | F98: The Central Baptist Church of Baltimore City | G98: Free community food distribution; held in front of the church. No eligibility documentation, referral, or intake requirements are stated in the available sources. | H98: FREE Community Food Distribution — Tuesday & Thursdays, 2:00 PM (in front of the church) Next Sunday Service — 9:45 AM Church School — Saturdays, 11:00 AM until 12:00 PM Adult S.E.E.D. Curriculum — Sundays, 8:15 AM | I98: Food & Essential Needs | J98: A church-based community center (Gift of Love Center at Central Baptist Church) that operates a free community food pantry/food distribution and also hosts regular worship services and church educational programs. | K98: http://www.thecentralbaptistchurch.org/ | L98: Google reviewers consistently praise the location’s food assistance and the supportive, community-oriented staff/volunteers, and several reviewers recount positive spiritual or personal support experiences. There are very few lower-rated or non-detailed reviews and no recurring service complaints visible in the fetched sample. The most recent reviews remain positive and align with the general pattern of community support. | M98: 77.611374 | N98: 68.888488 | O98: accepted google identity: 14.2/15; review volume: 25.2/30; review consistency: 4.3/7; review freshness: 7.5/8; verified website: 14.2/15; confirmed irs record: 0.0/20; source corroboration: 3.3/5; Synthesis metadata: high (not part of numeric confidence) | P98: 8312026 | Q98: =IF(OR(ISBLANK(M98), ISBLANK(N98)), "", IF(N98 < Sheet3!$B$6, "Insufficient Reviews", IF(M98 >= Sheet3!$B$2, "Highly Reliable", IF(M98 >= Sheet3!$B$3, "Reliable", IF(M98 >= Sheet3!$B$4, "Mixed Reviews", "Low Reliability"))))) -> Reliable
A99: =A98+1 -> 98 | B99: 120 N Front St, Baltimore, MD 21202 | C99: 39.291365 | D99: -76.606322 | E99: (410) 962-5078 | F99: St. Vincent de Paul Church | G99: Military Veterans Only | H99: Monday: 9:30 AM to 4:30 PM; Tuesday: 9:30 AM to 4:30 PM; Wednesday: 9:30 AM to 4:30 PM; Thursday: 9:30 AM to 4:30 PM; Friday: Closed; Saturday: Closed; Sunday: 9 to 10:30 AM | I99: Food & Essential Needs | J99: St. Vincent de Paul Church in Baltimore operates parish ministries that include an on-site food distribution/food pantry (Saint Vincent’s Emergency Services / Food Distribution Center) and other community service programs such as a resource exchange, Friday night dinners, and a men’s clothing ministry. | K99: http://www.stvchurch.org/ | L99: Google Maps reviewers most often highlight a warm, community-oriented parish with friendly and caring volunteers and positive experiences of parish-run meals and services. A smaller number of reviews express neutral or mild criticisms about worship style or other personal preferences, but complaints are infrequent. Recent reviews show a similar mix of appreciation with occasional neutral notes, indicating consistent user sentiment over time. | M99: 79.21563 | N99: 74.272894 | O99: accepted google identity: 14.2/15; review volume: 30.0/30; review consistency: 4.6/7; review freshness: 7.9/8; verified website: 14.2/15; confirmed irs record: 0.0/20; source corroboration: 3.3/5; Synthesis metadata: high (not part of numeric confidence) | P99: 8312026 | Q99: =IF(OR(ISBLANK(M99), ISBLANK(N99)), "", IF(N99 < Sheet3!$B$6, "Insufficient Reviews", IF(M99 >= Sheet3!$B$2, "Highly Reliable", IF(M99 >= Sheet3!$B$3, "Reliable", IF(M99 >= Sheet3!$B$4, "Mixed Reviews", "Low Reliability"))))) -> Reliable
A100: =A99+1 -> 99 | B100: 4 S Gay St, Baltimore, MD 21202 | C100: 39.289466 | D100: -76.609116 | E100: (410) 685-5252 | F100: Grace and Hope Mission - Food Distribution Center | G100: Appointment required; eligibility required. | H100: Monday: 3 to 5 PM; Tuesday: 3 to 5 PM; Wednesday: Closed; Thursday: 3 to 5 PM; Friday: 3 to 5 PM; Saturday: Closed; Sunday: Closed | I100: Food & Essential Needs | J100: A physical food distribution site that, per its Google Maps profile, offers grocery pickup/food distribution and accepts food and monetary donations. | L100: The Google Maps listing provides structured hours, a phone number, and notes that services are by appointment and subject to eligibility requirements, but there is no verified website or registry match to corroborate those details. Public feedback is extremely limited: the available reviewer comment is a short positive remark expressing gratitude and gives no operational detail. Given the sparse corroboration, callers should confirm hours and intake procedures by phone before relying on the listing. | M100: 76.768119 | N100: 35.364914 | O100: accepted google identity: 14.2/15; review volume: 7.3/30; review consistency: 7.0/7; review freshness: 5.2/8; verified website: 0.0/15; confirmed irs record: 0.0/20; source corroboration: 1.7/5; Synthesis metadata: insufficient_evidence (not part of numeric confidence) | P100: 8312026 | Q100: =IF(OR(ISBLANK(M100), ISBLANK(N100)), "", IF(N100 < Sheet3!$B$6, "Insufficient Reviews", IF(M100 >= Sheet3!$B$2, "Highly Reliable", IF(M100 >= Sheet3!$B$3, "Reliable", IF(M100 >= Sheet3!$B$4, "Mixed Reviews", "Low Reliability"))))) -> Insufficient Reviews
A101: =A100+1 -> 100 | B101: 219 N Chester St, Baltimore, MD 21231 | C101: 39.294913 | D101: -76.587357 | E101: (410) 675-3288 | F101: The Door Food Pantry - Food Distribution Center | G101: The Google listing indicates there is an eligibility requirement but does not provide details about who qualifies or what documentation is needed. | H101: Monday: Closed; Tuesday: 11 AM to 12 PM; Wednesday: Closed; Thursday: 11 AM to 12 PM; Friday: Closed; Saturday: Closed; Sunday: Closed | I101: Food & Essential Needs | J101: In-person food distribution (food pantry) that offers on-site grocery pickup and distributes pantry items including frozen meat according to the listing and reviewer reports. | L101: Google reviewer feedback is generally positive: reviewers commonly note availability of pantry items and frozen meat and describe the organization as a helpful neighborhood resource. A minority of reviews are lower-rated or provide little detail, so some concerns are reported but not described. The Google listing supplies hours and service options, but no independent website verification or registry match was found to further corroborate official status. | M101: 70.096303 | N101: 43.49294 | O101: accepted google identity: 14.2/15; review volume: 18.0/30; review consistency: 2.8/7; review freshness: 6.9/8; verified website: 0.0/15; confirmed irs record: 0.0/20; source corroboration: 1.7/5; Synthesis metadata: medium (not part of numeric confidence) | P101: 8312026 | Q101: =IF(OR(ISBLANK(M101), ISBLANK(N101)), "", IF(N101 < Sheet3!$B$6, "Insufficient Reviews", IF(M101 >= Sheet3!$B$2, "Highly Reliable", IF(M101 >= Sheet3!$B$3, "Reliable", IF(M101 >= Sheet3!$B$4, "Mixed Reviews", "Low Reliability"))))) -> Reliable
A102: =A101+1 -> 101 | B102: 4301 Raspe Ave, Baltimore, MD 21206 | C102: 39.349073 | D102: -76.534767 | E102: (410) 485-7654 | F102: Epiphany Lutheran | G102: Worship services are open to all; the website states Holy Communion is offered at most services and everyone is invited. Google Maps indicates wheelchair-accessible entrance, parking, and restrooms. Reviewers report volunteer-run food/clothing distributions; no documented intake, referral, eligibility paperwork, or registration process is provided in the available sources. | H102: Monday: 9 AM to 3:30 PM; Tuesday: 9 AM to 3:30 PM; Wednesday: 9 AM to 3:30 PM, 6 to 7:30 PM; Thursday: 9 AM to 3:30 PM; Friday: 9 AM to 3:30 PM; Saturday: 5 to 6 PM; Sunday: 9 to 10 AM, 10:30 AM to 12 PM | I102: Youth, Family, & General Support Services | J102: A local Lutheran congregation that holds regular in-person worship services and community activities. Reviewers report the congregation is welcoming and that volunteers operate periodic distributions of food, clothing, and toys for people in need. | K102: http://www.god-is-love.org/ | L102: Reviewers repeatedly describe the congregation and staff as welcoming and supportive, and multiple reviewers describe volunteering and service activities that provide food and clothing to community members. There is at least one detailed negative report about a volunteer’s behavior and customer-service interactions, indicating an isolated but notable concern. The most recent reviews trend positive, and the organization’s identity is corroborated by a current registry match and a church website that lists worship schedule details. | M102: 77.428419 | N102: 89.818234 | O102: accepted google identity: 14.2/15; review volume: 27.6/30; review consistency: 3.5/7; review freshness: 5.2/8; verified website: 14.2/15; confirmed irs record: 20.0/20; source corroboration: 5.0/5; Synthesis metadata: high (not part of numeric confidence) | P102: 8312026 | Q102: =IF(OR(ISBLANK(M102), ISBLANK(N102)), "", IF(N102 < Sheet3!$B$6, "Insufficient Reviews", IF(M102 >= Sheet3!$B$2, "Highly Reliable", IF(M102 >= Sheet3!$B$3, "Reliable", IF(M102 >= Sheet3!$B$4, "Mixed Reviews", "Low Reliability"))))) -> Reliable
A103: =A102+1 -> 102 | B103: 2612 Wilkens Ave, Baltimore, MD 21223 | C103: 39.279331 | D103: -76.656553 | E103: (410) 947-4988 | F103: Benedict's Pantry | G103: Website states the pantry runs monthly distributions (4th Saturday of every month, 10am–12pm). The site notes an eligibility requirement but does not specify details. The website lists a contact for inquiries; Google Maps also shows Saturday hours and indicates grocery pickup is offered. | H103: Monday: Closed; Tuesday: Closed; Wednesday: Closed; Thursday: Closed; Friday: Closed; Saturday: 10 AM to 12 PM; Sunday: Closed | I103: Food & Essential Needs | J103: A neighborhood pantry program operating from the Saint Benedict Neighborhood Center that provides food distribution and also helps people with clothing and household essentials through monthly pantry events and seasonal/holiday outreach. | K103: http://www.saintbenedict.org/guilds-and-organizations | L103: Available public review text is positive and describes the pantry helping with food, clothing, and household items; no recurring complaints appear in the small sample. The Saint Benedict Neighborhood Center website describes Benedict’s Pantry, monthly (4th-Saturday) pantry distributions, and seasonal outreach, which corroborates the listing. However, the online footprint is limited to the listing, the site content, and very few public reviews, and an IRS registry search did not return a match, so independent confirmation beyond these sources is limited. | M103: 79.019469 | N103: 52.719147 | O103: accepted google identity: 14.2/15; review volume: 7.3/30; review consistency: 7.0/7; review freshness: 6.6/8; verified website: 14.2/15; confirmed irs record: 0.0/20; source corroboration: 3.3/5; Synthesis metadata: medium (not part of numeric confidence) | P103: 8312026 | Q103: =IF(OR(ISBLANK(M103), ISBLANK(N103)), "", IF(N103 < Sheet3!$B$6, "Insufficient Reviews", IF(M103 >= Sheet3!$B$2, "Highly Reliable", IF(M103 >= Sheet3!$B$3, "Reliable", IF(M103 >= Sheet3!$B$4, "Mixed Reviews", "Low Reliability"))))) -> Reliable
...

Sheet Sheet3
A1: Key:
A2: Highly Reliable threshold | B2: 82
A3: Reliable | B3: 70
A4: Mixed Reviews | B4: 60
A6: confidence thresh | B6: 40
